{"type":"Topology","objects":{"zipcodes":{"type":"GeometryCollection","bbox":[-83.353928,32.034569,-78.547187,35.21554],"geometries":[{"type":"MultiPolygon","properties":{"zip":"29841"},"id":4529841,"arcs":[[[0]],[[1,2,3,4]]]},{"type":"Polygon","properties":{"zip":"29831"},"id":4529831,"arcs":[[5,6,7,8,9]]},{"type":"Polygon","properties":{"zip":"29146"},"id":4529146,"arcs":[[10,11,12,13,14,15,16,17]]},{"type":"Polygon","properties":{"zip":"29856"},"id":4529856,"arcs":[[18,19,20,-18,21,22],[23]]},{"type":"Polygon","properties":{"zip":"29673"},"id":4529673,"arcs":[[24,25,26,27,28,29,30]]},{"type":"Polygon","properties":{"zip":"29657"},"id":4529657,"arcs":[[31,32,33,34,35,36,37,38]]},{"type":"Polygon","properties":{"zip":"29817"},"id":4529817,"arcs":[[39,40,41,42,43,-16,44]]},{"type":"Polygon","properties":{"zip":"29843"},"id":4529843,"arcs":[[45,46,47,48,49]]},{"type":"Polygon","properties":{"zip":"29432"},"id":4529432,"arcs":[[50,51,52,53,54,55]]},{"type":"Polygon","properties":{"zip":"29481"},"id":4529481,"arcs":[[56,57,-53,58,59,60]]},{"type":"Polygon","properties":{"zip":"29945"},"id":4529945,"arcs":[[61,62,63,64,65,66,67,68,69,70,71,72,73]]},{"type":"Polygon","properties":{"zip":"29915"},"id":4529915,"arcs":[[74,75,76,77]]},{"type":"Polygon","properties":{"zip":"29928"},"id":4529928,"arcs":[[78,79,-75,80,81]]},{"type":"Polygon","properties":{"zip":"29904"},"id":4529904,"arcs":[[82]]},{"type":"MultiPolygon","properties":{"zip":"29483"},"id":4529483,"arcs":[[[83,84,85,86]],[[87,88,89,90,91,92,93],[94]]]},{"type":"MultiPolygon","properties":{"zip":"29456"},"id":4529456,"arcs":[[[95]],[[96]],[[97,98,99,-88,100]]]},{"type":"Polygon","properties":{"zip":"29118"},"id":4529118,"arcs":[[101,102,103,104]]},{"type":"Polygon","properties":{"zip":"29407"},"id":4529407,"arcs":[[105,106,107,108,109,110]]},{"type":"Polygon","properties":{"zip":"29464"},"id":4529464,"arcs":[[111,112,113,114,115,116]]},{"type":"MultiPolygon","properties":{"zip":"29420"},"id":4529420,"arcs":[[[117]],[[118]],[[119],[-97],[120]],[[-99,121,122,123,124]]]},{"type":"MultiPolygon","properties":{"zip":"29341"},"id":4529341,"arcs":[[[125,126]],[[127,128,129,130,131]]]},{"type":"Polygon","properties":{"zip":"29712"},"id":4529712,"arcs":[[132,133,134,135,136,137]]},{"type":"Polygon","properties":{"zip":"29704"},"id":4529704,"arcs":[[138,139,140,-133]]},{"type":"Polygon","properties":{"zip":"29727"},"id":4529727,"arcs":[[141,142,143,144,145]]},{"type":"Polygon","properties":{"zip":"29741"},"id":4529741,"arcs":[[146,147,148,-143]]},{"type":"MultiPolygon","properties":{"zip":"29540"},"id":4529540,"arcs":[[[149]],[[150,151,152,153,154,155],[156]]]},{"type":"Polygon","properties":{"zip":"29547"},"id":4529547,"arcs":[[157,158,159]]},{"type":"MultiPolygon","properties":{"zip":"29567"},"id":4529567,"arcs":[[[160]],[[-159,161,162,163,164]]]},{"type":"Polygon","properties":{"zip":"29574"},"id":4529574,"arcs":[[165,166,167,168,169],[170]]},{"type":"Polygon","properties":{"zip":"29585"},"id":4529585,"arcs":[[171,172,173,174]]},{"type":"MultiPolygon","properties":{"zip":"29651"},"id":4529651,"arcs":[[[175]],[[176,177,178,179,180,181,182,183,184,185]]]},{"type":"Polygon","properties":{"zip":"29617"},"id":4529617,"arcs":[[186,187,188,189,190,191]]},{"type":"Polygon","properties":{"zip":"29605"},"id":4529605,"arcs":[[192,193,194,195,-25]]},{"type":"MultiPolygon","properties":{"zip":"29662"},"id":4529662,"arcs":[[[196]],[[197,198,199],[200]]]},{"type":"MultiPolygon","properties":{"zip":"29650"},"id":4529650,"arcs":[[[201]],[[-186,202,203],[204]]]},{"type":"Polygon","properties":{"zip":"29635"},"id":4529635,"arcs":[[205,206,207,208],[209]]},{"type":"MultiPolygon","properties":{"zip":"29661"},"id":4529661,"arcs":[[[210]],[[211,212,213,214,-206],[215]]]},{"type":"Polygon","properties":{"zip":"29683"},"id":4529683,"arcs":[[-216]]},{"type":"MultiPolygon","properties":{"zip":"29924"},"id":4529924,"arcs":[[[216]],[[217,218,219,220,221]]]},{"type":"Polygon","properties":{"zip":"29921"},"id":4529921,"arcs":[[222,223,224]]},{"type":"Polygon","properties":{"zip":"29911"},"id":4529911,"arcs":[[225,226,227,-221,228,229]]},{"type":"Polygon","properties":{"zip":"29577"},"id":4529577,"arcs":[[230,231,232,233,234,235]]},{"type":"Polygon","properties":{"zip":"29943"},"id":4529943,"arcs":[[236,237,238,239,240],[241]]},{"type":"MultiPolygon","properties":{"zip":"29010"},"id":4529010,"arcs":[[[242]],[[243]],[[244,245,246,247,248,249,250,251,252,253,254,255,256,257,258,259,260,261]],[[262]]]},{"type":"Polygon","properties":{"zip":"29384"},"id":4529384,"arcs":[[263,264,265,266,267,268,269]]},{"type":"Polygon","properties":{"zip":"29040"},"id":4529040,"arcs":[[-254,270,271,272,273,274],[275]]},{"type":"MultiPolygon","properties":{"zip":"29046"},"id":4529046,"arcs":[[[-263]],[[-249,-248,276,-250],[-243]]]},{"type":"Polygon","properties":{"zip":"29169"},"id":4529169,"arcs":[[277,278,279,280,281,282],[283]]},{"type":"MultiPolygon","properties":{"zip":"29844"},"id":4529844,"arcs":[[[284]],[[285,286,287]]]},{"type":"Polygon","properties":{"zip":"29840"},"id":4529840,"arcs":[[288,289,290,291,292,293]]},{"type":"Polygon","properties":{"zip":"29899"},"id":4529899,"arcs":[[294]]},{"type":"Polygon","properties":{"zip":"29546"},"id":4529546,"arcs":[[295,296,297,298,299,300,301,302]]},{"type":"Polygon","properties":{"zip":"29204"},"id":4529204,"arcs":[[303,304,305,306,307]]},{"type":"Polygon","properties":{"zip":"29374"},"id":4529374,"arcs":[[308,309,310,311,312,313,314]]},{"type":"MultiPolygon","properties":{"zip":"29376"},"id":4529376,"arcs":[[[315,316]],[[317]],[[-315,318,319,320]]]},{"type":"MultiPolygon","properties":{"zip":"29324"},"id":4529324,"arcs":[[[321]],[[322,323]]]},{"type":"Polygon","properties":{"zip":"29375"},"id":4529375,"arcs":[[324]]},{"type":"MultiPolygon","properties":{"zip":"29518"},"id":4529518,"arcs":[[[325]],[[326,327,328]]]},{"type":"Polygon","properties":{"zip":"29564"},"id":4529564,"arcs":[[329,330,331,332]]},{"type":"Polygon","properties":{"zip":"29726"},"id":4529726,"arcs":[[333,334,335,336]]},{"type":"Polygon","properties":{"zip":"29638"},"id":4529638,"arcs":[[337,338,339,340,341]]},{"type":"Polygon","properties":{"zip":"29006"},"id":4529006,"arcs":[[342,343,344,345,346,347,348,349]]},{"type":"Polygon","properties":{"zip":"29812"},"id":4529812,"arcs":[[350,-46,351,352,353,-8,354,355,-41]]},{"type":"Polygon","properties":{"zip":"29631"},"id":4529631,"arcs":[[356,357,358,359,360,361]]},{"type":"Polygon","properties":{"zip":"29042"},"id":4529042,"arcs":[[362,363,364,-47,-351,-40]]},{"type":"Polygon","properties":{"zip":"29082"},"id":4529082,"arcs":[[-57,365,366,367]]},{"type":"Polygon","properties":{"zip":"29905"},"id":4529905,"arcs":[[368,369,370,371,372]]},{"type":"Polygon","properties":{"zip":"29909"},"id":4529909,"arcs":[[373,374,375,376,377,378]]},{"type":"Polygon","properties":{"zip":"29941"},"id":4529941,"arcs":[[379,380,381,-62,382],[383]]},{"type":"Polygon","properties":{"zip":"29907"},"id":4529907,"arcs":[[-371,384,385,386,387,388,389,-73,390,391]]},{"type":"Polygon","properties":{"zip":"29445"},"id":4529445,"arcs":[[392,393,-101,-94,394,395,396,397,398],[399]]},{"type":"Polygon","properties":{"zip":"29453"},"id":4529453,"arcs":[[400,401,402,403,404,405,406,407]]},{"type":"Polygon","properties":{"zip":"29438"},"id":4529438,"arcs":[[408,409,410,411,412,413,414]]},{"type":"Polygon","properties":{"zip":"29439"},"id":4529439,"arcs":[[415,416]]},{"type":"Polygon","properties":{"zip":"29487"},"id":4529487,"arcs":[[417,-410,418]]},{"type":"Polygon","properties":{"zip":"29714"},"id":4529714,"arcs":[[419,420,-134,-141,421,422],[423]]},{"type":"Polygon","properties":{"zip":"29729"},"id":4529729,"arcs":[[-421,424,425,426,427,-137,428,-135]]},{"type":"Polygon","properties":{"zip":"29728"},"id":4529728,"arcs":[[429,430,431,-146,432]]},{"type":"Polygon","properties":{"zip":"29536"},"id":4529536,"arcs":[[-158,433,434,435,436,437,438,-162],[-161]]},{"type":"Polygon","properties":{"zip":"29563"},"id":4529563,"arcs":[[439,440,441,-435]]},{"type":"Polygon","properties":{"zip":"29581"},"id":4529581,"arcs":[[442,443,444,445,-168,446,-441]]},{"type":"Polygon","properties":{"zip":"29845"},"id":4529845,"arcs":[[447,448,-288,449,450],[-285]]},{"type":"Polygon","properties":{"zip":"29130"},"id":4529130,"arcs":[[451,452,453,454,455,456]]},{"type":"Polygon","properties":{"zip":"29541"},"id":4529541,"arcs":[[457,458,459,460,461,462,463]]},{"type":"Polygon","properties":{"zip":"29576"},"id":4529576,"arcs":[[-173,464,465,466,467],[468],[469],[470]]},{"type":"MultiPolygon","properties":{"zip":"29440"},"id":4529440,"arcs":[[[471]],[[472,473,474,475,-175,476,477,-403,478]]]},{"type":"MultiPolygon","properties":{"zip":"29609"},"id":4529609,"arcs":[[[479,480]],[[481,482,483,484,485,-191,486,-189,487,488],[489]]]},{"type":"MultiPolygon","properties":{"zip":"29690"},"id":4529690,"arcs":[[[-490]],[[490,491,-488,-188,492,-213,493],[-211]]]},{"type":"Polygon","properties":{"zip":"29356"},"id":4529356,"arcs":[[494,495,-178,496,-491]]},{"type":"Polygon","properties":{"zip":"29568"},"id":4529568,"arcs":[[497,498,499,500,501,502,-231,503],[504]]},{"type":"MultiPolygon","properties":{"zip":"29936"},"id":4529936,"arcs":[[[-242]],[[-65,505,-63,-382,506,-374,507,-238,508,509,510]]]},{"type":"Polygon","properties":{"zip":"29720"},"id":4529720,"arcs":[[-431,511,512,513,-422,-140,514,515,516,517]]},{"type":"Polygon","properties":{"zip":"29645"},"id":4529645,"arcs":[[518,519,520,521,522,523]]},{"type":"MultiPolygon","properties":{"zip":"29355"},"id":4529355,"arcs":[[[524,525,526,527,528]],[[529,530,531,532,533]]]},{"type":"Polygon","properties":{"zip":"29063"},"id":4529063,"arcs":[[534,535,536,537,538]]},{"type":"Polygon","properties":{"zip":"29210"},"id":4529210,"arcs":[[539,540,-281,541,542]]},{"type":"Polygon","properties":{"zip":"29516"},"id":4529516,"arcs":[[543,544,545,-153,546]]},{"type":"Polygon","properties":{"zip":"29691"},"id":4529691,"arcs":[[547,548,549,550,551,552]]},{"type":"MultiPolygon","properties":{"zip":"29229"},"id":4529229,"arcs":[[[553]],[[554]],[[555,556,557,558,559]]]},{"type":"Polygon","properties":{"zip":"29225"},"id":4529225,"arcs":[[560,561,562]]},{"type":"Polygon","properties":{"zip":"29166"},"id":4529166,"arcs":[[563,-347,564,565]]},{"type":"Polygon","properties":{"zip":"29301"},"id":4529301,"arcs":[[566,567,568,-316,569,570,571],[572],[573],[574],[575]]},{"type":"MultiPolygon","properties":{"zip":"29385"},"id":4529385,"arcs":[[[576]],[[577,578,579]],[[580,581,582,-567,583,584],[585]]]},{"type":"MultiPolygon","properties":{"zip":"29369"},"id":4529369,"arcs":[[[-573]],[[586,-571,587,-320,588]]]},{"type":"MultiPolygon","properties":{"zip":"29378"},"id":4529378,"arcs":[[[-574]],[[-575]]]},{"type":"Polygon","properties":{"zip":"29062"},"id":4529062,"arcs":[[589,590,591,592]]},{"type":"Polygon","properties":{"zip":"29321"},"id":4529321,"arcs":[[-312,593,594,595]]},{"type":"Polygon","properties":{"zip":"29556"},"id":4529556,"arcs":[[596,597,-329,598,599,600,601],[-326]]},{"type":"Polygon","properties":{"zip":"29708"},"id":4529708,"arcs":[[602,603,604,605]]},{"type":"Polygon","properties":{"zip":"29733"},"id":4529733,"arcs":[[606,607]]},{"type":"Polygon","properties":{"zip":"29654"},"id":4529654,"arcs":[[608,609,-523,610,-342,611,612,613]]},{"type":"MultiPolygon","properties":{"zip":"29639"},"id":4529639,"arcs":[[[614]],[[615,616,-612,-341]]]},{"type":"Polygon","properties":{"zip":"29655"},"id":4529655,"arcs":[[617,618,619,-613,-617,620,621,622,623],[624],[-615]]},{"type":"Polygon","properties":{"zip":"29692"},"id":4529692,"arcs":[[-338,-611,-522,625,-265,626]]},{"type":"MultiPolygon","properties":{"zip":"29137"},"id":4529137,"arcs":[[[627]],[[-11,-21,628,629]],[[630,631,632,633,634,-13,635]]]},{"type":"Polygon","properties":{"zip":"29164"},"id":4529164,"arcs":[[-636,-12,-630,636,-343,637,638,-631],[-628]]},{"type":"Polygon","properties":{"zip":"29805"},"id":4529805,"arcs":[[-637,-629,-20,639,640,641,-344]]},{"type":"Polygon","properties":{"zip":"29129"},"id":4529129,"arcs":[[-346,642,-641,643,644,645,-565],[646]]},{"type":"Polygon","properties":{"zip":"29851"},"id":4529851,"arcs":[[647,648,649,650,651,652,653,654]]},{"type":"Polygon","properties":{"zip":"29834"},"id":4529834,"arcs":[[655,-648,656,657,658,-650]]},{"type":"Polygon","properties":{"zip":"29642"},"id":4529642,"arcs":[[659,-30,-35,660]]},{"type":"MultiPolygon","properties":{"zip":"29689"},"id":4529689,"arcs":[[[661]],[[662,663,664,665,666]]]},{"type":"Polygon","properties":{"zip":"29081"},"id":4529081,"arcs":[[667,-227,668,669,-49,670,-54,-58,-368]]},{"type":"Polygon","properties":{"zip":"29906"},"id":4529906,"arcs":[[-381,671,-389,672,673,-369,674,-375,-507],[675],[-83]]},{"type":"MultiPolygon","properties":{"zip":"29940"},"id":4529940,"arcs":[[[-384]],[[-380,-383,-74,-390,-672]]]},{"type":"Polygon","properties":{"zip":"29926"},"id":4529926,"arcs":[[676,-377,677,678,-82]]},{"type":"Polygon","properties":{"zip":"29461"},"id":4529461,"arcs":[[679,680,681,682,-395,-93]]},{"type":"MultiPolygon","properties":{"zip":"29410"},"id":4529410,"arcs":[[[-400]],[[-399,683,-393],[684]]]},{"type":"Polygon","properties":{"zip":"29469"},"id":4529469,"arcs":[[685,686,-680,-92]]},{"type":"MultiPolygon","properties":{"zip":"29472"},"id":4529472,"arcs":[[[687]],[[688,689,690,691,692,-90,693,694,695]]]},{"type":"Polygon","properties":{"zip":"29047"},"id":4529047,"arcs":[[696,697,698,699]]},{"type":"Polygon","properties":{"zip":"29449"},"id":4529449,"arcs":[[700,-419,-409,701,702,703]]},{"type":"Polygon","properties":{"zip":"29323"},"id":4529323,"arcs":[[704,705,-127,706,-131,707,708,709,710,711,712,713]]},{"type":"Polygon","properties":{"zip":"29001"},"id":4529001,"arcs":[[714,715,716,717]]},{"type":"Polygon","properties":{"zip":"29051"},"id":4529051,"arcs":[[718,719,720,721,722,-718]]},{"type":"Polygon","properties":{"zip":"29506"},"id":4529506,"arcs":[[723,-154,-546,724,725,726,727,728]]},{"type":"Polygon","properties":{"zip":"29592"},"id":4529592,"arcs":[[729,730],[731]]},{"type":"Polygon","properties":{"zip":"29543"},"id":4529543,"arcs":[[732,-436,-442,-447,-167]]},{"type":"Polygon","properties":{"zip":"29018"},"id":4529018,"arcs":[[733,-51,734,735,736,737,738,739,740]]},{"type":"Polygon","properties":{"zip":"29835"},"id":4529835,"arcs":[[741,742,-451,743,-294,744,745],[-295]]},{"type":"Polygon","properties":{"zip":"29838"},"id":4529838,"arcs":[[746,-286,-449,747,748]]},{"type":"MultiPolygon","properties":{"zip":"29615"},"id":4529615,"arcs":[[[-205]],[[-203,-185,749,750,751,-482,752],[-202]]]},{"type":"Polygon","properties":{"zip":"29918"},"id":4529918,"arcs":[[-219,753,754,-223,755,756,757,758,759]]},{"type":"Polygon","properties":{"zip":"29527"},"id":4529527,"arcs":[[760,761,762,-465,-172,-476,763,-300]]},{"type":"Polygon","properties":{"zip":"29569"},"id":4529569,"arcs":[[764,765,766,767,768,769,-445,770,771,-499,772]]},{"type":"MultiPolygon","properties":{"zip":"29588"},"id":4529588,"arcs":[[[773]],[[-471]],[[774,-235,775,-466,-763,776]]]},{"type":"MultiPolygon","properties":{"zip":"29544"},"id":4529544,"arcs":[[[-766,777]],[[-767,778]],[[779,780,-761,-299,781,-169,-446,-770,782,-768]]]},{"type":"Polygon","properties":{"zip":"29128"},"id":4529128,"arcs":[[-255,-275,783,-593,784,785,786]]},{"type":"Polygon","properties":{"zip":"29074"},"id":4529074,"arcs":[[787,-452,788,789]]},{"type":"Polygon","properties":{"zip":"29351"},"id":4529351,"arcs":[[-531,790]]},{"type":"Polygon","properties":{"zip":"29594"},"id":4529594,"arcs":[[791,792]]},{"type":"Polygon","properties":{"zip":"29678"},"id":4529678,"arcs":[[-360,793,-358,794,795,-667,796,797,798],[-662]]},{"type":"MultiPolygon","properties":{"zip":"29163"},"id":4529163,"arcs":[[[799]],[[800,801,802,803]]]},{"type":"Polygon","properties":{"zip":"29640"},"id":4529640,"arcs":[[-214,-493,-187,804,-661,-34,805]]},{"type":"MultiPolygon","properties":{"zip":"29671"},"id":4529671,"arcs":[[[-210]],[[806,-207,-215,-806,-33,807,808],[809]]]},{"type":"MultiPolygon","properties":{"zip":"29685"},"id":4529685,"arcs":[[[-810]],[[-208,-807,-809,810,811,812]]]},{"type":"Polygon","properties":{"zip":"29223"},"id":4529223,"arcs":[[813,814,-560,815,816,-308,817],[-554],[-555]]},{"type":"Polygon","properties":{"zip":"29147"},"id":4529147,"arcs":[[-814,818]]},{"type":"Polygon","properties":{"zip":"29202"},"id":4529202,"arcs":[[819,820]]},{"type":"Polygon","properties":{"zip":"29349"},"id":4529349,"arcs":[[-180,821,-714,822,823,-582,824],[825]]},{"type":"Polygon","properties":{"zip":"29316"},"id":4529316,"arcs":[[-713,826,-823]]},{"type":"Polygon","properties":{"zip":"29373"},"id":4529373,"arcs":[[827,828]]},{"type":"Polygon","properties":{"zip":"29329"},"id":4529329,"arcs":[[-324,829]]},{"type":"Polygon","properties":{"zip":"29154"},"id":4529154,"arcs":[[830,-272,831,832,833,834,835,-590,-784,-274]]},{"type":"Polygon","properties":{"zip":"29580"},"id":4529580,"arcs":[[-600,836,837,-474,838]]},{"type":"Polygon","properties":{"zip":"29717"},"id":4529717,"arcs":[[839,840,841,842]]},{"type":"MultiPolygon","properties":{"zip":"29628"},"id":4529628,"arcs":[[[843,844,-292]],[[-622,845,-290,846]]]},{"type":"Polygon","properties":{"zip":"29659"},"id":4529659,"arcs":[[-625]]},{"type":"Polygon","properties":{"zip":"29627"},"id":4529627,"arcs":[[847,848,-614,-620,849]]},{"type":"Polygon","properties":{"zip":"29809"},"id":4529809,"arcs":[[850]]},{"type":"Polygon","properties":{"zip":"29684"},"id":4529684,"arcs":[[851,852,853,-624]]},{"type":"Polygon","properties":{"zip":"29621"},"id":4529621,"arcs":[[854,855,856,857,-850,-619],[858]]},{"type":"Polygon","properties":{"zip":"29927"},"id":4529927,"arcs":[[-239,-508,-379,859,-77,860]]},{"type":"Polygon","properties":{"zip":"29135"},"id":4529135,"arcs":[[861,862,863,864,865,866,867,868,869,-102]]},{"type":"Polygon","properties":{"zip":"29412"},"id":4529412,"arcs":[[-109,870,871,872,-416,873,874]]},{"type":"Polygon","properties":{"zip":"29702"},"id":4529702,"arcs":[[875,876,877,878,-842,879,-128,880]]},{"type":"Polygon","properties":{"zip":"29593"},"id":4529593,"arcs":[[881,-151,882,883,884]]},{"type":"Polygon","properties":{"zip":"29009"},"id":4529009,"arcs":[[885,886,887,-260,888,-258,889]]},{"type":"Polygon","properties":{"zip":"29446"},"id":4529446,"arcs":[[890,891,892,-414,893,-391,-72],[894]]},{"type":"MultiPolygon","properties":{"zip":"29475"},"id":4529475,"arcs":[[[-70,895]],[[896,-68,897,-366,-61],[898]]]},{"type":"Polygon","properties":{"zip":"29493"},"id":4529493,"arcs":[[-899]]},{"type":"Polygon","properties":{"zip":"29069"},"id":4529069,"arcs":[[899,900,901,902,903,-246]]},{"type":"Polygon","properties":{"zip":"29079"},"id":4529079,"arcs":[[-901,904]]},{"type":"MultiPolygon","properties":{"zip":"29565"},"id":4529565,"arcs":[[[-732]],[[905,-731,906,-725,-545,907,-438]]]},{"type":"Polygon","properties":{"zip":"29477"},"id":4529477,"arcs":[[908,909,910,911,912,-741]]},{"type":"Polygon","properties":{"zip":"29832"},"id":4529832,"arcs":[[913,-566,-646,914,915]]},{"type":"Polygon","properties":{"zip":"29554"},"id":4529554,"arcs":[[916,917,-301,-764,-475,-838]]},{"type":"Polygon","properties":{"zip":"29687"},"id":4529687,"arcs":[[-497,-177,-204,-753,-489,-492]]},{"type":"Polygon","properties":{"zip":"29644"},"id":4529644,"arcs":[[918,919,-524,-610,920,921]]},{"type":"Polygon","properties":{"zip":"29923"},"id":4529923,"arcs":[[922,-230,923]]},{"type":"Polygon","properties":{"zip":"29572"},"id":4529572,"arcs":[[924,925,-232,-503]]},{"type":"MultiPolygon","properties":{"zip":"29575"},"id":4529575,"arcs":[[[-469]],[[-470]],[[-776,-234,926,-467]]]},{"type":"MultiPolygon","properties":{"zip":"29511"},"id":4529511,"arcs":[[[-783,-769]],[[-779,-778,-765,927,-780]]]},{"type":"MultiPolygon","properties":{"zip":"29032"},"id":4529032,"arcs":[[[-889,-259]],[[928,-890,-257,929]]]},{"type":"Polygon","properties":{"zip":"29058"},"id":4529058,"arcs":[[930,931,-790,932,933,-513]]},{"type":"Polygon","properties":{"zip":"29325"},"id":4529325,"arcs":[[934,935,-532,-791,-530,-529,936,937,938]]},{"type":"Polygon","properties":{"zip":"29360"},"id":4529360,"arcs":[[939,-938,940,-266,-626,-521]]},{"type":"Polygon","properties":{"zip":"29388"},"id":4529388,"arcs":[[941,-589,-319,-314,942,-519,-920,943,-183,944],[945],[-325]]},{"type":"Polygon","properties":{"zip":"29335"},"id":4529335,"arcs":[[-313,-596,946,-939,-940,-520,-943],[947]]},{"type":"Polygon","properties":{"zip":"29104"},"id":4529104,"arcs":[[-252,948,-720,949]]},{"type":"MultiPolygon","properties":{"zip":"29153"},"id":4529153,"arcs":[[[-276]],[[-832,-271,-253,-950,-719,-717,950,951]]]},{"type":"MultiPolygon","properties":{"zip":"29070"},"id":4529070,"arcs":[[[952]],[[953,954,955,-638,-350]]]},{"type":"MultiPolygon","properties":{"zip":"29571"},"id":4529571,"arcs":[[[956]],[[-171]],[[-170,-782,-298,957,-296,958,-726,-907,-730,-906,-437,-733,-166]]]},{"type":"Polygon","properties":{"zip":"29108"},"id":4529108,"arcs":[[-525,-534,959,960,961,962,963]]},{"type":"Polygon","properties":{"zip":"29126"},"id":4529126,"arcs":[[964,965,966,967,968,969,-961]]},{"type":"Polygon","properties":{"zip":"29676"},"id":4529676,"arcs":[[-812,970,971,972,-552,973,974]]},{"type":"Polygon","properties":{"zip":"29665"},"id":4529665,"arcs":[[975]]},{"type":"Polygon","properties":{"zip":"29107"},"id":4529107,"arcs":[[-14,-635,976,-104,977,978,979]]},{"type":"Polygon","properties":{"zip":"29039"},"id":4529039,"arcs":[[980,981,982]]},{"type":"MultiPolygon","properties":{"zip":"29206"},"id":4529206,"arcs":[[[983]],[[984,985,986,-304,-817]]]},{"type":"MultiPolygon","properties":{"zip":"29205"},"id":4529205,"arcs":[[[987]],[[-561,988,-821,989,990]],[[-305,-987,991,992]]]},{"type":"Polygon","properties":{"zip":"29207"},"id":4529207,"arcs":[[-985,-816,-559,993,994,995,996,997],[-984]]},{"type":"Polygon","properties":{"zip":"29152"},"id":4529152,"arcs":[[-273,-831]]},{"type":"Polygon","properties":{"zip":"29353"},"id":4529353,"arcs":[[998,999,1000,1001,1002,1003,-594,-311,1004],[1005]]},{"type":"Polygon","properties":{"zip":"29732"},"id":4529732,"arcs":[[1006,-603,1007,-607,1008,1009],[1010]]},{"type":"Polygon","properties":{"zip":"29860"},"id":4529860,"arcs":[[1011,-2,1012,1013,1014,1015],[-1]]},{"type":"Polygon","properties":{"zip":"29853"},"id":4529853,"arcs":[[1016,-22,-17,-44,1017,-42,-356]]},{"type":"Polygon","properties":{"zip":"29849"},"id":4529849,"arcs":[[-50,-670,1018,1019,-352]]},{"type":"MultiPolygon","properties":{"zip":"29902"},"id":4529902,"arcs":[[[-676]],[[-386,1020]],[[-388,1021,-673]],[[1022,-678,-376,-675,-373]]]},{"type":"Polygon","properties":{"zip":"29935"},"id":4529935,"arcs":[[-387,-1021,-385,-370,-674,-1022]]},{"type":"Polygon","properties":{"zip":"29053"},"id":4529053,"arcs":[[1023,1024,1025,1026,1027,1028,1029]]},{"type":"MultiPolygon","properties":{"zip":"29414"},"id":4529414,"arcs":[[[1030]],[[-111,1031,-85,1032,-124,1033,1034]]]},{"type":"Polygon","properties":{"zip":"29455"},"id":4529455,"arcs":[[-110,-875,1035,-411,-418,-701,1036,-86,-1032],[-1031]]},{"type":"Polygon","properties":{"zip":"29405"},"id":4529405,"arcs":[[-106,-1035,1037,1038,1039,1040]]},{"type":"Polygon","properties":{"zip":"29418"},"id":4529418,"arcs":[[1041,1042,1043,-1038,-1034,-123]]},{"type":"Polygon","properties":{"zip":"29466"},"id":4529466,"arcs":[[1044,-112,1045,1046]]},{"type":"Polygon","properties":{"zip":"29409"},"id":4529409,"arcs":[[1047]]},{"type":"Polygon","properties":{"zip":"29424"},"id":4529424,"arcs":[[1048,1049]]},{"type":"Polygon","properties":{"zip":"29307"},"id":4529307,"arcs":[[-711,1050,1051,1052,-829,1053,1054,1055,1056,1057,1058,1059],[-322],[-830,-323]]},{"type":"Polygon","properties":{"zip":"29014"},"id":4529014,"arcs":[[1060,1061,1062,1063,1064,-426]]},{"type":"Polygon","properties":{"zip":"29101"},"id":4529101,"arcs":[[-888,1065,1066,1067,-261]]},{"type":"Polygon","properties":{"zip":"29584"},"id":4529584,"arcs":[[1068,-884,1069,-1067,1070,-144,-149,1071]]},{"type":"Polygon","properties":{"zip":"29111"},"id":4529111,"arcs":[[1072,1073,-327,-598,1074,1075,-715,-723]]},{"type":"Polygon","properties":{"zip":"29162"},"id":4529162,"arcs":[[1076,1077,-1073,-722,1078]]},{"type":"MultiPolygon","properties":{"zip":"29114"},"id":4529114,"arcs":[[[1079]],[[1080,1081,1082,1083,-1077,1084]]]},{"type":"MultiPolygon","properties":{"zip":"29488"},"id":4529488,"arcs":[[[-895]],[[-896,-69,-897,-60,1085,-912,1086,-891,-71]]]},{"type":"Polygon","properties":{"zip":"29448"},"id":4529448,"arcs":[[-740,1087,-691,1088,-909]]},{"type":"Polygon","properties":{"zip":"29437"},"id":4529437,"arcs":[[-1089,-690,1089,1090,-910]]},{"type":"Polygon","properties":{"zip":"29180"},"id":4529180,"arcs":[[-789,-457,1091,1092,-537,1093,1094,1095,-1062,1096,-933]]},{"type":"Polygon","properties":{"zip":"29065"},"id":4529065,"arcs":[[1097,-1095,1098,1099,-967]]},{"type":"Polygon","properties":{"zip":"29015"},"id":4529015,"arcs":[[1100,1101,-1063,-1096,-1098,-966]]},{"type":"Polygon","properties":{"zip":"29583"},"id":4529583,"arcs":[[1102,-727,-959,-303,1103,1104,1105,1106,-462]]},{"type":"Polygon","properties":{"zip":"29555"},"id":4529555,"arcs":[[-302,-918,1107,-1104]]},{"type":"Polygon","properties":{"zip":"29530"},"id":4529530,"arcs":[[1108,-464,1109]]},{"type":"Polygon","properties":{"zip":"29322"},"id":4529322,"arcs":[[1110,-705,-822,-179,-496]]},{"type":"Polygon","properties":{"zip":"29939"},"id":4529939,"arcs":[[1111,-757]]},{"type":"Polygon","properties":{"zip":"29934"},"id":4529934,"arcs":[[-224,-755,1112,-509,-237,1113]]},{"type":"Polygon","properties":{"zip":"29579"},"id":4529579,"arcs":[[1114,-504,-236,-775]]},{"type":"Polygon","properties":{"zip":"29582"},"id":4529582,"arcs":[[-502,1115,1116,-925]]},{"type":"MultiPolygon","properties":{"zip":"29078"},"id":4529078,"arcs":[[[1117]],[[-454,1118,-786,1119,-995,1120]]]},{"type":"Polygon","properties":{"zip":"29067"},"id":4529067,"arcs":[[1121,-931,-512,-430,1122,-886,-929,1123,1124]]},{"type":"MultiPolygon","properties":{"zip":"29080"},"id":4529080,"arcs":[[[-1085,-1079,-721,-949,-251,-277,-247,-904,1125,-1081]],[[-1080]]]},{"type":"MultiPolygon","properties":{"zip":"29170"},"id":4529170,"arcs":[[[-284]],[[1126,1127,-1030,1128,-278]]]},{"type":"Polygon","properties":{"zip":"29172"},"id":4529172,"arcs":[[-1128,1129,1130,-1024]]},{"type":"MultiPolygon","properties":{"zip":"29054"},"id":4529054,"arcs":[[[1131]],[[1132,1133,1134,1135,-955]]]},{"type":"Polygon","properties":{"zip":"29122"},"id":4529122,"arcs":[[-1100,1136,-968]]},{"type":"Polygon","properties":{"zip":"29696"},"id":4529696,"arcs":[[-973,1137,-553]]},{"type":"Polygon","properties":{"zip":"29686"},"id":4529686,"arcs":[[1138,-974,-551,1139]]},{"type":"Polygon","properties":{"zip":"29142"},"id":4529142,"arcs":[[1140,-801,1141,-738,1142,-700]]},{"type":"Polygon","properties":{"zip":"29113"},"id":4529113,"arcs":[[-15,-980,1143,-363,-45]]},{"type":"Polygon","properties":{"zip":"29038"},"id":4529038,"arcs":[[-364,-1144,-979,1144,-982,1145,1146]]},{"type":"Polygon","properties":{"zip":"29117"},"id":4529117,"arcs":[[1147]]},{"type":"MultiPolygon","properties":{"zip":"29682"},"id":4529682,"arcs":[[[1148]],[[-32,1149,1150,1151,-971,-811,-808]]]},{"type":"Polygon","properties":{"zip":"29634"},"id":4529634,"arcs":[[-794,-359]]},{"type":"Polygon","properties":{"zip":"29209"},"id":4529209,"arcs":[[1152,1153,-992,-986,-998,1154,-1025,-1131],[-988]]},{"type":"Polygon","properties":{"zip":"29044"},"id":4529044,"arcs":[[-996,-1120,-785,-592,1155,-866,1156,1157]]},{"type":"Polygon","properties":{"zip":"29061"},"id":4529061,"arcs":[[1158,-864,1159,-1026,-1155,-997,-1158]]},{"type":"Polygon","properties":{"zip":"29302"},"id":4529302,"arcs":[[-310,1160,1161,-1057,1162,-1055,1163,-1005]]},{"type":"Polygon","properties":{"zip":"29377"},"id":4529377,"arcs":[[-578,-585,1164]]},{"type":"Polygon","properties":{"zip":"29346"},"id":4529346,"arcs":[[-1163,-1056]]},{"type":"Polygon","properties":{"zip":"29333"},"id":4529333,"arcs":[[1165,-1059]]},{"type":"MultiPolygon","properties":{"zip":"29819"},"id":4529819,"arcs":[[[1166,1167,1168]],[[1169,1170,1171,-746]]]},{"type":"Polygon","properties":{"zip":"29829"},"id":4529829,"arcs":[[-651,-659,1172,-3,-1012,1173,1174,1175]]},{"type":"Polygon","properties":{"zip":"29842"},"id":4529842,"arcs":[[1176,-4,-1173,-658,1177,-654,1178,-6]]},{"type":"Polygon","properties":{"zip":"29836"},"id":4529836,"arcs":[[-9,-354,1179,1180]]},{"type":"Polygon","properties":{"zip":"29827"},"id":4529827,"arcs":[[1181,-1019,-669,-226,-923,1182]]},{"type":"Polygon","properties":{"zip":"29611"},"id":4529611,"arcs":[[-660,-805,-192,-486,1183,-193,-31]]},{"type":"Polygon","properties":{"zip":"29826"},"id":4529826,"arcs":[[-43,-1018]]},{"type":"Polygon","properties":{"zip":"29910"},"id":4529910,"arcs":[[-677,-81,-78,-860,-378]]},{"type":"Polygon","properties":{"zip":"29112"},"id":4529112,"arcs":[[-862,-105,-977,-634,1184]]},{"type":"Polygon","properties":{"zip":"29458"},"id":4529458,"arcs":[[-404,-478,1185,1186]]},{"type":"Polygon","properties":{"zip":"29482"},"id":4529482,"arcs":[[1187,-114,1188,1189,-872]]},{"type":"Polygon","properties":{"zip":"29470"},"id":4529470,"arcs":[[-1037,-704,1190,-695,1191,-87]]},{"type":"Polygon","properties":{"zip":"29403"},"id":4529403,"arcs":[[1192,-1049,1193,-107,-1041,1194,-116],[-1048]]},{"type":"Polygon","properties":{"zip":"29401"},"id":4529401,"arcs":[[-1050,-1193,-115,-1188,-871,-108,-1194]]},{"type":"Polygon","properties":{"zip":"29423"},"id":4529423,"arcs":[[1195]]},{"type":"Polygon","properties":{"zip":"29330"},"id":4529330,"arcs":[[1196,-1051,-710,1197,-708,-130]]},{"type":"Polygon","properties":{"zip":"29706"},"id":4529706,"arcs":[[1198,1199,1200,1201,-336,1202,-427,-1065]]},{"type":"MultiPolygon","properties":{"zip":"29055"},"id":4529055,"arcs":[[[-424]],[[-423,-514,-934,-1097,-1061,-425,-420]]]},{"type":"Polygon","properties":{"zip":"29031"},"id":4529031,"arcs":[[1203,-1199,-1064,-1102,1204]]},{"type":"Polygon","properties":{"zip":"29742"},"id":4529742,"arcs":[[-1202,1205,1206,-1003,1207,-840,1208,1209,-337]]},{"type":"Polygon","properties":{"zip":"29520"},"id":4529520,"arcs":[[1210,1211,1212,-885,-1069,1213]]},{"type":"Polygon","properties":{"zip":"29550"},"id":4529550,"arcs":[[-262,-1068,-1070,-883,-156,1214,1215,-902,-905,-900,-245],[-244]]},{"type":"Polygon","properties":{"zip":"29474"},"id":4529474,"arcs":[[-911,-1091,1216,1217,1218,-892,-1087]]},{"type":"Polygon","properties":{"zip":"29452"},"id":4529452,"arcs":[[-1219,1219,-702,-415,-893]]},{"type":"Polygon","properties":{"zip":"29435"},"id":4529435,"arcs":[[-1090,-689,1220,-1217]]},{"type":"Polygon","properties":{"zip":"29161"},"id":4529161,"arcs":[[-1126,-903,-1216,1221,1222,-459,1223,-1082]]},{"type":"Polygon","properties":{"zip":"29138"},"id":4529138,"arcs":[[-564,-914,1224,1225,1226,1227,1228,-963,1229,-348]]},{"type":"MultiPolygon","properties":{"zip":"29591"},"id":4529591,"arcs":[[[-1110,-463,-1107]],[[1230,-1083,-1224,-458,-1109,-1106,1231]],[[1232]]]},{"type":"MultiPolygon","properties":{"zip":"29607"},"id":4529607,"arcs":[[[-201]],[[1233,-200,1234,-195,1235,-484,1236,-480,1237,-751],[-197],[1238],[1239],[1240]]]},{"type":"Polygon","properties":{"zip":"29680"},"id":4529680,"arcs":[[-196,-1235,-199,1241,-922,1242,-26]]},{"type":"Polygon","properties":{"zip":"29601"},"id":4529601,"arcs":[[-1184,-485,-1236,-194]]},{"type":"Polygon","properties":{"zip":"29613"},"id":4529613,"arcs":[[-487,-190]]},{"type":"MultiPolygon","properties":{"zip":"29848"},"id":4529848,"arcs":[[[1243,-742,1244,-1168,1245,-1226]],[[-293,-845,1246,-1170,-745]]]},{"type":"Polygon","properties":{"zip":"29666"},"id":4529666,"arcs":[[1247,1248,-1227,-1246,-1167,1249]]},{"type":"Polygon","properties":{"zip":"29916"},"id":4529916,"arcs":[[-66,-511,1250]]},{"type":"Polygon","properties":{"zip":"29944"},"id":4529944,"arcs":[[1251,-1251,-510,-1113,-754,-218],[-217]]},{"type":"MultiPolygon","properties":{"zip":"29566"},"id":4529566,"arcs":[[[-505]],[[-501,1252,-1116]]]},{"type":"Polygon","properties":{"zip":"29020"},"id":4529020,"arcs":[[-930,-256,-787,-1119,-453,-788,-932,-1122,1253,-1124]]},{"type":"MultiPolygon","properties":{"zip":"29707"},"id":4529707,"arcs":[[[1254]],[[1255,-517,1256]]]},{"type":"Polygon","properties":{"zip":"29073"},"id":4529073,"arcs":[[-279,-1129,-1029,1257,-1135,1258],[1259],[1260]]},{"type":"Polygon","properties":{"zip":"29123"},"id":4529123,"arcs":[[-1028,1261,-632,-639,-956,-1136,-1258]]},{"type":"Polygon","properties":{"zip":"29570"},"id":4529570,"arcs":[[1262,-792,1263,1264,-164,1265]]},{"type":"Polygon","properties":{"zip":"29037"},"id":4529037,"arcs":[[-1228,-1249,1266,1267,-527,1268]]},{"type":"Polygon","properties":{"zip":"29145"},"id":4529145,"arcs":[[-526,-964,-1229,-1269]]},{"type":"Polygon","properties":{"zip":"29693"},"id":4529693,"arcs":[[1269,1270,1271,1272,-549,1273,-798]]},{"type":"Polygon","properties":{"zip":"29672"},"id":4529672,"arcs":[[-972,-1152,1274,-361,-799,-1274,-548,-1138],[-976]]},{"type":"Polygon","properties":{"zip":"29664"},"id":4529664,"arcs":[[-1140,-550,-1273,1275,1276]]},{"type":"Polygon","properties":{"zip":"29133"},"id":4529133,"arcs":[[-735,-56,1277,-1146,-981,1278]]},{"type":"Polygon","properties":{"zip":"29115"},"id":4529115,"arcs":[[-103,-870,1279,-736,-1279,-983,-1145,-978],[-1148]]},{"type":"Polygon","properties":{"zip":"29048"},"id":4529048,"arcs":[[1280,-803,1281,1282]]},{"type":"Polygon","properties":{"zip":"29203"},"id":4529203,"arcs":[[-556,-815,-819,-818,-307,1283,-540,1284,-538,-1093,1285]]},{"type":"Polygon","properties":{"zip":"29201"},"id":4529201,"arcs":[[-306,-993,-1154,1286,-282,-541,-1284],[-990,-820,-989,-563,1287]]},{"type":"Polygon","properties":{"zip":"29052"},"id":4529052,"arcs":[[-1157,-865,-1159]]},{"type":"MultiPolygon","properties":{"zip":"29303"},"id":4529303,"arcs":[[[-586]],[[-824,-827,-712,-1060,-1166,-1058,-1162,1288,-568,-583]]]},{"type":"Polygon","properties":{"zip":"29365"},"id":4529365,"arcs":[[-580,1289,-181,-825,-581],[-577]]},{"type":"Polygon","properties":{"zip":"29168"},"id":4529168,"arcs":[[1290,-867,-1156,-591,-836]]},{"type":"Polygon","properties":{"zip":"29590"},"id":4529590,"arcs":[[1291,-331,1292,-602]]},{"type":"MultiPolygon","properties":{"zip":"29710"},"id":4529710,"arcs":[[[1293,-877]],[[1294,1295,1296,-878]],[[-876,1297,1298,1299,1300,1301],[1302],[1303]]]},{"type":"MultiPolygon","properties":{"zip":"29745"},"id":4529745,"arcs":[[[-1301,1304]],[[1305,-1296]],[[-1303]],[[-1011]],[[-1304]],[[1306,-1295,-1294,-1302]],[[1307,-1299,1308,-604,-1007,-1010,1309,-334,-1210]]]},{"type":"Polygon","properties":{"zip":"29620"},"id":4529620,"arcs":[[-1171,-1247,-844,-291,-846,-621,-616,-340,1310,1311,1312]]},{"type":"Polygon","properties":{"zip":"29801"},"id":4529801,"arcs":[[-652,-1176,1313,1314,-644,-640,-19,1315]]},{"type":"Polygon","properties":{"zip":"29850"},"id":4529850,"arcs":[[-1175,1316,-1314]]},{"type":"Polygon","properties":{"zip":"29810"},"id":4529810,"arcs":[[-1180,-353,-1020,-1182,1317,1318]]},{"type":"Polygon","properties":{"zip":"29626"},"id":4529626,"arcs":[[1319,-853,1320,-664,1321]]},{"type":"Polygon","properties":{"zip":"29697"},"id":4529697,"arcs":[[-848,-858,1322,-28,1323],[1324],[1325]]},{"type":"MultiPolygon","properties":{"zip":"29625"},"id":4529625,"arcs":[[[-859]],[[-796,1326,-856,1327,-1322,-663]]]},{"type":"Polygon","properties":{"zip":"29630"},"id":4529630,"arcs":[[-1150,-39,1328,-37,1329,-362,-1275,-1151],[-1149]]},{"type":"Polygon","properties":{"zip":"29436"},"id":4529436,"arcs":[[1330,-686,-91,-693,1331,-1283,1332,1333],[-688]]},{"type":"Polygon","properties":{"zip":"29059"},"id":4529059,"arcs":[[-1281,-1332,-692,-1088,-739,-1142,-804],[-800]]},{"type":"Polygon","properties":{"zip":"29468"},"id":4529468,"arcs":[[1334,1335,1336,1337,1338,-1334]]},{"type":"Polygon","properties":{"zip":"29030"},"id":4529030,"arcs":[[1339,-697,-1143,-737,-1280,-869]]},{"type":"Polygon","properties":{"zip":"29160"},"id":4529160,"arcs":[[-1160,-863,-1185,-633,-1262,-1027]]},{"type":"Polygon","properties":{"zip":"29429"},"id":4529429,"arcs":[[1340,1341,-405,-1187,1342,1343,-1047]]},{"type":"Polygon","properties":{"zip":"29451"},"id":4529451,"arcs":[[1344,-1189,-113,-1045,-1344]]},{"type":"Polygon","properties":{"zip":"29426"},"id":4529426,"arcs":[[-1220,-1218,-1221,-696,-1191,-703]]},{"type":"Polygon","properties":{"zip":"29340"},"id":4529340,"arcs":[[-1052,-1197,-129,-880,-841,-1208,-1002,1345,-1000,1346]]},{"type":"MultiPolygon","properties":{"zip":"29372"},"id":4529372,"arcs":[[[-1001,-1346]],[[-1054,-828,-1053,-1347,-999,-1164]]]},{"type":"Polygon","properties":{"zip":"29730"},"id":4529730,"arcs":[[-1008,1347,-515,-139,-138,-428,-1203,-335,-1310,-1009,-608]]},{"type":"Polygon","properties":{"zip":"29724"},"id":4529724,"arcs":[[-136,-429]]},{"type":"Polygon","properties":{"zip":"29102"},"id":4529102,"arcs":[[1348,-834,1349,-951,-716,-1076,1350,-1336,1351]]},{"type":"Polygon","properties":{"zip":"29148"},"id":4529148,"arcs":[[-699,1352,-1352,-1335,-1333,-1282,-802,-1141]]},{"type":"Polygon","properties":{"zip":"29125"},"id":4529125,"arcs":[[-835,-1349,-1353,-698,-1340,-868,-1291]]},{"type":"MultiPolygon","properties":{"zip":"29560"},"id":4529560,"arcs":[[[-1233]],[[-1074,-1078,-1084,-1231,-1232,-1105,-1108,-917,-837,-599,-328]]]},{"type":"Polygon","properties":{"zip":"29929"},"id":4529929,"arcs":[[-668,-367,-898,-67,-1252,-222,-228]]},{"type":"Polygon","properties":{"zip":"29501"},"id":4529501,"arcs":[[1353,-729,1354,-460,-1223]]},{"type":"Polygon","properties":{"zip":"29821"},"id":4529821,"arcs":[[1355,-749,1356,-1014]]},{"type":"Polygon","properties":{"zip":"29505"},"id":4529505,"arcs":[[-728,-1103,-461,-1355]]},{"type":"Polygon","properties":{"zip":"29510"},"id":4529510,"arcs":[[-479,-402,1357,-332,-1292,-601,-839,-473],[-472]]},{"type":"MultiPolygon","properties":{"zip":"29681"},"id":4529681,"arcs":[[[-1239]],[[-1240]],[[-1241]],[[-750,-184,-944,-919,-1242,-198,-1234]]]},{"type":"Polygon","properties":{"zip":"29045"},"id":4529045,"arcs":[[-455,-1121,-994,-558,1358],[-1118]]},{"type":"Polygon","properties":{"zip":"29175"},"id":4529175,"arcs":[[-1125,-1254]]},{"type":"Polygon","properties":{"zip":"29370"},"id":4529370,"arcs":[[-937,-528,-1268,1359,-267,-941]]},{"type":"Polygon","properties":{"zip":"29178"},"id":4529178,"arcs":[[-1205,-1101,-965,-960,-533,-936,1360]]},{"type":"MultiPolygon","properties":{"zip":"29072"},"id":4529072,"arcs":[[[-1260]],[[-1261]],[[1361,1362,-542,-280,-1259,-1134],[-1132]]]},{"type":"Polygon","properties":{"zip":"29075"},"id":4529075,"arcs":[[1363,-969,-1137,-1099,-1094,-536,1364]]},{"type":"Polygon","properties":{"zip":"29212"},"id":4529212,"arcs":[[1365,-539,-1285,-543,-1363]]},{"type":"Polygon","properties":{"zip":"29519"},"id":4529519,"arcs":[[-297,-958],[-957]]},{"type":"Polygon","properties":{"zip":"29512"},"id":4529512,"arcs":[[-1264,-793,-1263,1366,-547,-152,-882,-1213,1367,1368]]},{"type":"Polygon","properties":{"zip":"29596"},"id":4529596,"arcs":[[-1212,1369,-1368]]},{"type":"Polygon","properties":{"zip":"29368"},"id":4529368,"arcs":[[-709,-1198]]},{"type":"Polygon","properties":{"zip":"29150"},"id":4529150,"arcs":[[-952,-1350,-833]]},{"type":"MultiPolygon","properties":{"zip":"29379"},"id":4529379,"arcs":[[[-1006]],[[-1004,-1207,1370,-1200,-1204,-1361,-935,-947,-595]]]},{"type":"Polygon","properties":{"zip":"29364"},"id":4529364,"arcs":[[-1206,-1201,-1371]]},{"type":"Polygon","properties":{"zip":"29715"},"id":4529715,"arcs":[[-606,1371,-1257,-516,-1348],[-1255]]},{"type":"Polygon","properties":{"zip":"29653"},"id":4529653,"arcs":[[-264,1372,-1311,-339,-627]]},{"type":"MultiPolygon","properties":{"zip":"29649"},"id":4529649,"arcs":[[[1373]],[[-1312,-1373,-270,1374]]]},{"type":"Polygon","properties":{"zip":"29646"},"id":4529646,"arcs":[[-1313,-1375,-269,1375,-1250,-1169,-1245,-1172],[-1374]]},{"type":"Polygon","properties":{"zip":"29847"},"id":4529847,"arcs":[[-1016,1376,-915,-645,-1315,-1317,-1174]]},{"type":"MultiPolygon","properties":{"zip":"29803"},"id":4529803,"arcs":[[[-24]],[[-1179,-653,-1316,-23,-1017,-355,-7],[-851]]]},{"type":"MultiPolygon","properties":{"zip":"29105"},"id":4529105,"arcs":[[[-647]],[[-345,-642,-643]]]},{"type":"Polygon","properties":{"zip":"29816"},"id":4529816,"arcs":[[-655,-1178,-657]]},{"type":"Polygon","properties":{"zip":"29828"},"id":4529828,"arcs":[[-649,-656]]},{"type":"Polygon","properties":{"zip":"29932"},"id":4529932,"arcs":[[-924,-229,-220,-760,1377,-1318,-1183]]},{"type":"Polygon","properties":{"zip":"29624"},"id":4529624,"arcs":[[-1328,-855,-618,-854,-1320]]},{"type":"Polygon","properties":{"zip":"29670"},"id":4529670,"arcs":[[-1330,-36,-29,-1323,-857,-1327,-795,-357]]},{"type":"MultiPolygon","properties":{"zip":"29669"},"id":4529669,"arcs":[[[-1325]],[[-1326]],[[-1324,-27,-1243,-921,-609,-849]]]},{"type":"Polygon","properties":{"zip":"29643"},"id":4529643,"arcs":[[1378,-1270,-797,-666]]},{"type":"Polygon","properties":{"zip":"29003"},"id":4529003,"arcs":[[-1147,-1278,-55,-671,-48,-365]]},{"type":"MultiPolygon","properties":{"zip":"29920"},"id":4529920,"arcs":[[[-79,-679,-1023,-372,-392,-894,-413,1379]]]},{"type":"MultiPolygon","properties":{"zip":"29431"},"id":4529431,"arcs":[[[1380]],[[-681,-687,-1331,-1339,1381,-408,1382]]]},{"type":"Polygon","properties":{"zip":"29479"},"id":4529479,"arcs":[[-1338,-333,-1358,-401,-1382]]},{"type":"Polygon","properties":{"zip":"29492"},"id":4529492,"arcs":[[1383,-397,1384,-1341,-1046,-117,-1195,-1040]]},{"type":"Polygon","properties":{"zip":"29450"},"id":4529450,"arcs":[[-396,-683,1385,-406,-1342,-1385]]},{"type":"Polygon","properties":{"zip":"29434"},"id":4529434,"arcs":[[-407,-1386,-682,-1383],[-1381]]},{"type":"MultiPolygon","properties":{"zip":"29406"},"id":4529406,"arcs":[[[-685]],[[-1042,-122,-98,-394,-684,-398,-1384,-1039,-1044,1386],[-1196]]]},{"type":"MultiPolygon","properties":{"zip":"29485"},"id":4529485,"arcs":[[[-95]],[[-121]],[[-100,-125,-1033,-84,-1192,-694,-89],[-118],[-96],[-119],[-120]]]},{"type":"Polygon","properties":{"zip":"29404"},"id":4529404,"arcs":[[-1387,-1043]]},{"type":"Polygon","properties":{"zip":"29718"},"id":4529718,"arcs":[[-145,-1071,-1066,-887,-1123,-433]]},{"type":"Polygon","properties":{"zip":"29709"},"id":4529709,"arcs":[[-1214,-1072,-148,1387]]},{"type":"Polygon","properties":{"zip":"29056"},"id":4529056,"arcs":[[-1075,-597,-1293,-330,-1337,-1351]]},{"type":"MultiPolygon","properties":{"zip":"29532"},"id":4529532,"arcs":[[[-157]],[[-155,-724,-1354,-1222,-1215],[-150]]]},{"type":"Polygon","properties":{"zip":"29471"},"id":4529471,"arcs":[[-734,-913,-1086,-59,-52]]},{"type":"Polygon","properties":{"zip":"29824"},"id":4529824,"arcs":[[-1225,-916,-1377,-1015,-1357,-748,-448,-743,-1244]]},{"type":"Polygon","properties":{"zip":"29016"},"id":4529016,"arcs":[[-456,-1359,-557,-1286,-1092]]},{"type":"Polygon","properties":{"zip":"29614"},"id":4529614,"arcs":[[-1237,-483,-752,-1238,-481]]},{"type":"Polygon","properties":{"zip":"29922"},"id":4529922,"arcs":[[1388,-758,-1112,-756,-225,-1114,-241]]},{"type":"Polygon","properties":{"zip":"29526"},"id":4529526,"arcs":[[-773,-498,-1115,-777,-762,-781,-928],[-774]]},{"type":"Polygon","properties":{"zip":"29545"},"id":4529545,"arcs":[[1389,-771,-444]]},{"type":"Polygon","properties":{"zip":"29912"},"id":4529912,"arcs":[[-506,-64]]},{"type":"Polygon","properties":{"zip":"29332"},"id":4529332,"arcs":[[-1267,-1248,-1376,-268,-1360]]},{"type":"Polygon","properties":{"zip":"29033"},"id":4529033,"arcs":[[-1127,-283,-1287,-1153,-1130]]},{"type":"Polygon","properties":{"zip":"29036"},"id":4529036,"arcs":[[-535,-1366,-1362,-1133,1390,-1365]]},{"type":"Polygon","properties":{"zip":"29525"},"id":4529525,"arcs":[[-1266,-163,-439,-908,-544,-1367]]},{"type":"Polygon","properties":{"zip":"29127"},"id":4529127,"arcs":[[-970,-1364,-1391,-954,-349,-1230,-962],[-953]]},{"type":"Polygon","properties":{"zip":"29658"},"id":4529658,"arcs":[[-1272,1391,-1276]]},{"type":"Polygon","properties":{"zip":"29667"},"id":4529667,"arcs":[[-38,-1329]]},{"type":"Polygon","properties":{"zip":"29208"},"id":4529208,"arcs":[[1287,990,561]]},{"type":"Polygon","properties":{"zip":"29306"},"id":4529306,"arcs":[[-569,-1289,-1161,-309,-321,-588,-570,-317],[-318]]},{"type":"MultiPolygon","properties":{"zip":"29334"},"id":4529334,"arcs":[[[-946]],[[-1290,-579,-1165,-584,-572,-587,-942,-945,-182],[-176]]]},{"type":"Polygon","properties":{"zip":"29331"},"id":4529331,"arcs":[[-948]]},{"type":"Polygon","properties":{"zip":"29320"},"id":4529320,"arcs":[[-576]]},{"type":"Polygon","properties":{"zip":"29338"},"id":4529338,"arcs":[[-826]]},{"type":"Polygon","properties":{"zip":"29743"},"id":4529743,"arcs":[[-879,-1297,-1306,-1307,-1305,-1300,-1308,-1209,-843]]}]}},"arcs":[[[283014,474273],[0,0]],[[279088,470775],[25241,15880]],[[304329,486655],[-712,-24328]],[[303617,462327],[-6494,-13640]],[[297123,448687],[-18035,22088]],[[299505,440344],[17092,-16699]],[[316597,423645],[26033,-746],[9146,-34509]],[[351776,388390],[-4907,-5679]],[[346869,382711],[-14651,-16918]],[[332218,365793],[-39340,54320],[6627,20231]],[[403738,467745],[13788,14468]],[[417526,482213],[2563,-1524]],[[420089,480689],[20408,-9521]],[[440497,471168],[5715,-18741]],[[446212,452427],[-2290,-10762]],[[443922,441665],[-14323,9709]],[[429599,451374],[-22250,9784]],[[407349,461158],[-3611,6587]],[[370388,465013],[9802,15999]],[[380190,481012],[8934,-2834]],[[389124,478178],[14614,-10433]],[[407349,461158],[-20140,-8701],[-7179,-25251]],[[380030,427206],[-16629,1730],[6987,36077]],[[374265,451716],[0,0]],[[193081,865815],[20833,-22193]],[[213914,843622],[-2877,-15415]],[[211037,828207],[-50334,5821]],[[160703,834028],[-2808,2252]],[[157895,836280],[-597,3244]],[[157298,839524],[24022,26238]],[[181320,865762],[11761,53]],[[122636,871194],[-3476,5398]],[[119160,876592],[23244,6871]],[[142404,883463],[6563,-16021]],[[148967,867442],[8331,-27918]],[[157298,839524],[-20479,-3131]],[[136819,836393],[-11382,19470]],[[125437,855863],[-45,2768]],[[125392,858631],[-2756,12563]],[[461984,427275],[-17255,-14164],[-804,-23481]],[[443925,389630],[-28510,11844]],[[415415,401474],[1220,8587]],[[416635,410061],[-1391,17644]],[[415244,427705],[14355,23669]],[[443922,441665],[18062,-14390]],[[442321,354019],[1453,30984]],[[443774,385003],[24317,-12585]],[[468091,372418],[-3677,-28753]],[[464414,343665],[-5172,-15694]],[[459242,327971],[-16921,26048]],[[549569,398050],[6857,-18993]],[[556426,379057],[-15393,-12448],[12235,-18858]],[[553268,347751],[-21512,11375],[-30386,-9260]],[[501370,349866],[-2674,3723]],[[498696,353589],[14343,31818]],[[513039,385407],[9128,23628],[27402,-10985]],[[509264,322435],[-6477,13316]],[[502787,335751],[-1417,14115]],[[553268,347751],[9251,-15895]],[[562519,331856],[-15945,-7222]],[[546574,324634],[-37310,-2199]],[[524759,175675],[-3369,-19910]],[[521390,155765],[-15845,18139]],[[505545,173904],[-783,1192]],[[504762,175096],[-8913,16308]],[[495849,191404],[25377,27301],[-6538,19425]],[[514688,238130],[2068,25481]],[[516756,263611],[11059,-21308]],[[527815,242303],[3893,665]],[[531708,242968],[871,-1063]],[[532579,241905],[24732,-14608]],[[557311,227297],[3188,-45557],[31576,-33787]],[[592075,147953],[-9510,-1218]],[[582565,146735],[-30973,33673],[-26833,-4733]],[[525165,35528],[-835,-10691]],[[524330,24837],[-9003,-11021]],[[515327,13816],[-4736,10250]],[[510591,24066],[14574,11462]],[[561159,66820],[1473,-2750]],[[562632,64070],[-15126,-25098],[-23176,-14135]],[[525165,35528],[9056,14878]],[[534221,50406],[26938,16414]],[[548049,132638],[0,0]],[[651293,263662],[15366,11496]],[[666659,275158],[-6836,-14388]],[[659823,260770],[1636,-5791]],[[661459,254979],[-10166,8683]],[[680102,311886],[-9838,-5088]],[[670264,306798],[-25140,-13153]],[[645124,293645],[-8211,29844],[23110,25399],[-5903,21630]],[[654120,370518],[9543,7497]],[[663663,378015],[8051,-13882]],[[671714,364133],[-10435,-13230],[29551,-34110]],[[690830,316793],[-10728,-4907]],[[653463,300710],[0,0]],[[667167,289237],[0,0]],[[667045,287086],[0,0]],[[679667,301043],[2456,-7422]],[[682123,293621],[-8039,-3472]],[[674084,290149],[-3820,16649]],[[680102,311886],[-435,-10843]],[[502663,507862],[33656,-21612]],[[536319,486250],[-24740,-25770],[-22626,20120]],[[488953,480600],[-948,2258]],[[488005,482858],[14658,25004]],[[692563,251657],[12012,-2353]],[[704575,249304],[2157,-15072]],[[706732,234232],[1534,-1883]],[[708266,232349],[-11336,-2470]],[[696930,229879],[-6519,1920]],[[690411,231799],[2152,19858]],[[729104,266527],[9849,-23407]],[[738953,243120],[-1594,-9026]],[[737359,234094],[-22371,1036]],[[714988,235130],[149,4294]],[[715137,239424],[-244,7142]],[[714893,246566],[14211,19961]],[[672838,283440],[0,0]],[[673820,284129],[0,0]],[[667889,283440],[0,0]],[[667210,285590],[0,0]],[[682123,293621],[3362,-11742]],[[685485,281879],[-14041,-9426]],[[671444,272453],[-1143,-216]],[[670301,272237],[3783,17912]],[[312968,989841],[1150,-62]],[[314118,989779],[-1150,62]],[[362901,987041],[6891,-17780]],[[369792,969261],[-30890,-31825]],[[338902,937436],[-19136,35429]],[[319766,972865],[-3401,16785]],[[316365,989650],[46536,-2609]],[[496940,881021],[8136,-21912]],[[505076,859109],[-12574,-8342]],[[492502,850767],[-3909,11098]],[[488593,861865],[-1501,585]],[[487092,862450],[-4925,7344]],[[482167,869794],[14773,11227]],[[496940,881021],[18422,7269]],[[515362,888290],[-197,-34562]],[[515165,853728],[-10089,5381]],[[650760,873301],[3631,-38]],[[654391,873263],[-658,-46982]],[[653733,826281],[-10491,-11292]],[[643242,814989],[-13096,17409]],[[630146,832398],[6146,32731],[14468,8172]],[[654391,873263],[4978,-143]],[[659369,873120],[9724,-24469],[-7799,-26078]],[[661294,822573],[-7561,3708]],[[726742,720966],[0,0]],[[703970,765417],[33821,-14748],[12019,8854]],[[749810,759523],[5153,-10485]],[[754963,749038],[13989,-35226]],[[768952,713812],[-10878,8890]],[[758074,722702],[-53740,-1031]],[[704334,721671],[-364,43746]],[[717164,720309],[0,0]],[[856766,755471],[-13420,-5638],[-19744,21286]],[[823602,771119],[773,26855]],[[824375,797974],[32391,-42503]],[[822107,767075],[0,0]],[[823602,771119],[-20640,17612]],[[802962,788731],[7006,18583]],[[809968,807314],[2202,5790]],[[812170,813104],[12205,-15130]],[[839541,650379],[382,53711]],[[839923,704090],[21462,-5695]],[[861385,698395],[8743,-23392],[-10290,-23261]],[[859838,651742],[-11609,-20771]],[[848229,630971],[-8688,19408]],[[839541,650379],[0,0]],[[875414,510350],[10245,-18118]],[[885659,492232],[-6686,-29193],[11963,-3498]],[[890936,459541],[-14023,-30682]],[[876913,428859],[-15130,7805],[14537,23695],[-906,49991]],[[249668,896652],[0,0]],[[224862,912480],[-7355,43290]],[[217507,955770],[15891,-1903]],[[233398,953867],[2871,-9328]],[[236269,944539],[1810,-6718]],[[238079,937821],[7339,-18936]],[[245418,918885],[8958,-30469]],[[254376,888416],[-7952,-18497]],[[246424,869919],[-12106,8684]],[[234318,878603],[-476,7022]],[[233842,885625],[-8980,26855]],[[178432,897351],[-5746,19890]],[[172686,917241],[18369,-3325]],[[191055,913916],[230,-1137]],[[191285,912779],[-304,-7289]],[[190981,905490],[1511,-11875]],[[192492,893615],[-14060,3736]],[[193081,865815],[400,12581]],[[193481,878396],[9369,-551]],[[202850,877845],[11141,-30863]],[[213991,846982],[-77,-3360]],[[215738,869717],[0,0]],[[223351,866491],[-1266,-11526]],[[222085,854965],[-2457,2563]],[[219628,857528],[3723,8963]],[[215111,853443],[0,0]],[[223471,890496],[0,0]],[[233842,885625],[-13443,10577]],[[220399,896202],[4463,16278]],[[228340,889174],[0,0]],[[161538,977550],[16005,-5359],[-6435,-23922],[-17889,-9283]],[[153219,938986],[-28477,-722]],[[124742,938264],[-4295,14309]],[[120447,952573],[41091,24977]],[[151651,947954],[0,0]],[[179489,936553],[0,0]],[[161538,977550],[26156,8879]],[[187694,986429],[-3373,-43563],[-12033,-25532]],[[172288,917334],[-18267,4350]],[[154021,921684],[-802,17302]],[[179220,942757],[0,0]],[[471924,258647],[0,0]],[[491809,275328],[-20568,-10290],[-7373,-25406]],[[463868,239632],[-18443,3029]],[[445425,242661],[2892,8819]],[[448317,251480],[6085,20407],[31349,18656]],[[485751,290543],[6058,-15215]],[[447242,201914],[10413,2555]],[[457655,204469],[2652,-8459]],[[460307,196010],[-13065,5904]],[[437653,274088],[34941,37785]],[[472594,311873],[6040,-11653]],[[478634,300220],[7117,-9677]],[[448317,251480],[-4244,2817]],[[444073,254297],[-6420,19791]],[[937222,539199],[4373,2996]],[[941595,542195],[-1989,-10571]],[[939606,531624],[-20232,-26064]],[[919374,505560],[-9007,3735]],[[910367,509295],[3683,12988]],[[914050,522283],[23172,16916]],[[454836,162697],[14944,-10207]],[[469780,152490],[-12734,-31116]],[[457046,121374],[2739,-21728]],[[459785,99646],[-8973,35295],[-16923,20354]],[[433889,155295],[18459,-12481],[2488,19883]],[[455560,153551],[0,0]],[[663707,650692],[0,0]],[[660110,725947],[0,0]],[[660110,725947],[9653,-23100]],[[669763,702847],[-6903,-32500]],[[662860,670347],[2209,-11778]],[[665069,658569],[-1362,-7877]],[[663707,650692],[-700,-815]],[[663007,649877],[1202,-4060]],[[664209,645817],[-4464,-11126]],[[659745,634691],[-19629,12472]],[[640116,647163],[-12700,12943]],[[627416,660106],[-10664,8047]],[[616752,668153],[-1044,1018]],[[615708,669171],[-7400,31794]],[[608308,700965],[13480,19917]],[[621788,720882],[1215,544]],[[623003,721426],[13493,1126]],[[636496,722552],[1199,9792]],[[637695,732344],[18538,-4019]],[[656233,728325],[3877,-2378]],[[663007,649877],[0,0]],[[257952,714308],[-11566,8809]],[[246386,723117],[3260,25901]],[[249646,749018],[21079,-6756]],[[270725,742262],[5620,-13975]],[[276345,728287],[1098,-31218]],[[277443,697069],[-1089,2048]],[[276354,699117],[-18402,15191]],[[627416,660106],[-21694,-49395]],[[605722,610711],[-4453,3766]],[[601269,614477],[-5990,1313]],[[595279,615790],[-9992,244]],[[585287,616034],[22938,11502],[-8098,24263],[16625,16354]],[[618868,648192],[0,0]],[[665069,658569],[-860,-12752]],[[470293,604061],[-7028,13545]],[[463265,617606],[-827,7574]],[[462438,625180],[591,763]],[[463029,625943],[14260,-6421]],[[477289,619522],[2416,-4385]],[[479705,615137],[-9412,-11076]],[[466683,613680],[0,0]],[[236564,552882],[0,0]],[[239586,540591],[-8051,-5768]],[[231535,534823],[-7757,11532]],[[223778,546355],[15808,-5764]],[[170219,599997],[-12254,22210]],[[157965,622207],[19510,18268]],[[177475,640475],[17,0]],[[177492,640475],[4542,-14110]],[[182034,626365],[1875,-6272]],[[183909,620093],[-13690,-20096]],[[230916,596341],[0,0]],[[805513,607212],[675,23257],[20357,-974]],[[826545,629495],[7636,-11876]],[[834181,617619],[1907,-11024]],[[836088,606595],[16273,-28973]],[[852361,577622],[13851,-52244]],[[866212,525378],[-19291,3203],[-8597,26139]],[[838324,554720],[-32937,43531]],[[805387,598251],[126,8961]],[[493123,634026],[-703,-13613]],[[492420,620413],[-7008,-872]],[[485412,619541],[-2197,5424]],[[483215,624965],[5991,10245]],[[489206,635210],[3917,-1184]],[[301478,882368],[750,408]],[[302228,882776],[23120,-9978]],[[325348,872798],[2015,-23313]],[[327363,849485],[-7268,-6999]],[[320095,842486],[-16687,7515]],[[303408,850001],[-3031,1302]],[[300377,851303],[1101,31065]],[[288150,904044],[-21,2129]],[[288129,906173],[21,-2129]],[[293724,889706],[0,0]],[[300377,851303],[-19003,22137]],[[281374,873440],[7845,29653]],[[289219,903093],[12259,-20725]],[[318746,927889],[0,0]],[[316912,928809],[-200,-206]],[[316712,928603],[200,206]],[[257897,888915],[0,0]],[[719619,531190],[0,0]],[[711170,549356],[-1870,8851]],[[709300,558207],[9827,12006],[21945,-13830],[-3194,-25316]],[[737878,531067],[-26708,18289]],[[706014,458806],[2138,7630]],[[708152,466436],[41333,-17201]],[[749485,449235],[-24166,-9407]],[[725319,439828],[-19305,18978]],[[431001,899154],[22111,-1569]],[[453112,897585],[7247,-21752]],[[460359,875833],[-32622,455]],[[427737,876288],[3264,22866]],[[223343,757171],[5960,-25550]],[[229303,731621],[-16474,-25487]],[[212829,706134],[-9702,3853]],[[203127,709987],[-11306,15389]],[[191821,725376],[31522,31795]],[[404241,533319],[-21982,-12391]],[[382259,520928],[-2861,19742]],[[379398,540670],[-17346,50355]],[[362052,591025],[-6570,2850]],[[355482,593875],[-9170,9325]],[[346312,603200],[14628,36086]],[[360940,639286],[11876,3614]],[[372816,642900],[-3457,-32294],[25543,-42899],[9339,-34388]],[[443925,389630],[-151,-4627]],[[442321,354019],[-22885,-16496]],[[419436,337523],[-17301,-8214]],[[402135,329309],[-11909,29046],[-13935,-6003],[-29422,30359]],[[351776,388390],[30521,35298]],[[382297,423688],[13074,-24104],[20044,1890]],[[117825,829357],[-7326,-5745]],[[110499,823612],[-5870,4579]],[[104629,828191],[-564,3347]],[[104065,831538],[620,4142]],[[104685,835680],[146,1131]],[[104831,836811],[12994,-7454]],[[461984,427275],[10585,-5740]],[[472569,421535],[1760,-2207]],[[474329,419328],[-6238,-46910]],[[509264,322435],[6026,-34367]],[[515290,288068],[-26720,23895]],[[488570,311963],[14217,23788]],[[549422,102959],[5126,1954]],[[554548,104913],[2088,-109]],[[556636,104804],[3978,-8735]],[[560614,96069],[96,-703]],[[560710,95366],[-11288,7593]],[[497233,88013],[17945,9860],[12254,37105]],[[527432,134978],[15013,-36668]],[[542445,98310],[10086,-16335]],[[552531,81975],[-12957,1168]],[[539574,83143],[-22858,3228],[-27231,-20476]],[[489485,65895],[7748,22118]],[[530331,177278],[4568,-26325]],[[534899,150953],[-7567,-9056]],[[527332,141897],[-5942,13868]],[[524759,175675],[5572,1603]],[[530331,177278],[0,0]],[[556636,104804],[1038,4089]],[[557674,108893],[-587,4098]],[[557087,112991],[743,2146]],[[557830,115137],[-3184,17434]],[[554646,132571],[1995,14673]],[[556641,147244],[25924,-509]],[[592075,147953],[15063,-12667]],[[607138,135286],[-35503,-6130],[-11021,-33087]],[[692496,293308],[-3241,2334]],[[689255,295642],[-9588,5401]],[[690830,316793],[22972,7470]],[[713802,324263],[2246,-28875]],[[716048,295388],[-7652,-20774]],[[708396,274614],[-334,649]],[[708062,275263],[-15566,18045]],[[692496,293308],[0,0]],[[746987,396214],[4617,8611]],[[751604,404825],[13344,-5459]],[[764948,399366],[47915,-28761]],[[812863,370605],[-33777,-25274]],[[779086,345331],[-7521,-3955]],[[771565,341376],[-25463,18063]],[[746102,359439],[2117,17386]],[[748219,376825],[-1232,19389]],[[616743,194358],[24588,-8721]],[[641331,185637],[12908,-14369]],[[654239,171268],[3222,-7909]],[[657461,163359],[-39607,-36611]],[[617854,126748],[-1153,864]],[[616701,127612],[6826,16739]],[[623527,144351],[-12440,16527],[5656,33480]],[[702799,190015],[18353,16016]],[[721152,206031],[-18353,-16016]],[[662055,211678],[19984,-2427],[-27800,-37983]],[[641331,185637],[20724,26041]],[[510368,818415],[-8718,9169]],[[501650,827584],[-9148,23183]],[[515165,853728],[-3876,-36066]],[[511289,817662],[-921,753]],[[510368,818415],[0,0]],[[501650,827584],[-7059,-22897]],[[494591,804687],[-20361,8854]],[[474230,813541],[7690,54025]],[[481920,867566],[247,2228]],[[487092,862450],[1501,-585]],[[596702,843470],[-838,813]],[[595864,844283],[-14961,30578]],[[580903,874861],[69857,-1560]],[[630146,832398],[-33444,11072]],[[856766,755471],[3528,-4538]],[[860294,750933],[-5480,-34697]],[[854814,716236],[-17819,-10086]],[[836995,706150],[-3138,2048]],[[833857,708198],[-37438,63145]],[[796419,771343],[6543,17388]],[[860294,750933],[22851,-29045]],[[883145,721888],[-22473,-13340]],[[860672,708548],[-5858,7688]],[[883145,721888],[25106,-31824]],[[908251,690064],[-8182,-33912]],[[900069,656152],[-7372,-15069]],[[892697,641083],[-32859,10659]],[[861385,698395],[-713,10153]],[[258011,564389],[-5213,-8901]],[[252798,555488],[-13212,-14897]],[[223778,546355],[-7908,12705]],[[215870,559060],[34954,28257],[7187,-22928]],[[522069,751404],[12658,-7959]],[[534727,743445],[17797,-20518]],[[552524,722927],[-22852,-23129]],[[529672,699798],[-15011,474]],[[514661,700272],[-40206,-4087]],[[474455,696185],[10978,36877],[36636,18342]],[[737102,618393],[-7618,-6157]],[[729484,612236],[2999,52692]],[[732483,664928],[5557,1862]],[[738040,666790],[5564,-17319],[38083,-6124]],[[781687,643347],[-8613,-30422]],[[773074,612925],[-13926,10873]],[[759148,623798],[-22046,-5405]],[[885659,492232],[165,9332]],[[885824,501564],[18002,-4979]],[[903826,496585],[5528,-6710]],[[909354,489875],[-18418,-30334]],[[906105,492386],[0,0]],[[906989,491510],[0,0]],[[897955,498282],[0,0]],[[786760,405933],[0,0]],[[786760,405933],[22907,19196],[8091,35032],[-3756,29710]],[[814002,489871],[1652,9026]],[[815654,498897],[37425,-14903],[20641,27521]],[[873720,511515],[1694,-1165]],[[876913,428859],[-10151,-70597],[-21701,-20499]],[[845061,337763],[-32198,32842]],[[764948,399366],[21812,6567]],[[206955,892379],[-1422,-966]],[[205533,891413],[1422,966]],[[207737,899037],[-1321,-5106]],[[206416,893931],[-976,-2080]],[[205440,891851],[-3996,-3901]],[[201444,887950],[-7437,3519]],[[194007,891469],[-1515,2146]],[[190981,905490],[304,7289]],[[191055,913916],[16278,7763]],[[207333,921679],[404,-22642]],[[203665,918568],[0,0]],[[220718,993903],[-24384,-19086],[12281,-9670]],[[208615,965147],[-1282,-43468]],[[172686,917241],[-398,93]],[[187694,986429],[33024,7474]],[[220718,993903],[45144,-1816]],[[265862,992087],[-31030,-23763],[-1434,-14457]],[[217507,955770],[-8892,9377]],[[947344,557031],[-8358,30952]],[[938986,587983],[20912,36280]],[[959898,624263],[21993,-28189]],[[981891,596074],[-22317,-35189]],[[959574,560885],[-7366,-9068]],[[952208,551817],[-10613,-9622]],[[937222,539199],[10122,17832]],[[973334,584207],[0,0]],[[504762,175096],[783,-1192]],[[527332,141897],[100,-6919]],[[497233,88013],[-3202,17213],[-36985,16148]],[[469780,152490],[19499,21113],[-19582,12567]],[[469697,186170],[13623,11006]],[[483320,197176],[12529,-5772]],[[595864,844283],[-17523,-11455]],[[578341,832828],[-64152,-31133]],[[514189,801695],[-2900,15967]],[[515362,888290],[1768,25472]],[[517130,913762],[-196,1212]],[[516934,914974],[18123,-2921]],[[535057,912053],[-3213,-36479],[49059,-713]],[[266055,835874],[9233,-12716]],[[275288,823158],[8654,-24600]],[[283942,798558],[-12034,3647],[-33456,-34675]],[[238452,767530],[-2164,5393]],[[236288,772923],[-3770,17722]],[[232518,790645],[7259,26803],[26278,18426]],[[326244,732072],[-1282,-24925]],[[324962,707147],[-12314,-3160]],[[312648,703987],[-3872,12629]],[[308776,716616],[-4931,11384]],[[303845,728000],[22399,4072]],[[326244,732072],[-8037,12983]],[[318207,745055],[8420,5139]],[[326627,750194],[9739,3026]],[[336366,753220],[28287,-6685]],[[364653,746535],[-38409,-14463]],[[433751,649198],[3990,31779]],[[437741,680977],[495,745]],[[438236,681722],[14385,-8977]],[[452621,672745],[8570,-12956]],[[461191,659789],[-664,-13681],[-26776,3090]],[[468058,645914],[8191,-21489]],[[476249,624425],[1040,-4903]],[[463029,625943],[-3880,2065]],[[459149,628008],[8909,17906]],[[781387,791120],[14389,-21489]],[[795776,769631],[-21757,-58081]],[[774019,711550],[-5067,2262]],[[754963,749038],[26424,42082]],[[70809,845851],[-2504,-4202]],[[68305,841649],[-31531,1911],[-4185,12496]],[[32589,856056],[27658,32526]],[[60247,888582],[11234,3892]],[[71481,892474],[6326,-11610]],[[77807,880864],[-6998,-35013]],[[508820,660937],[0,0]],[[515063,651758],[0,0]],[[501239,658982],[-1156,5744]],[[500083,664726],[12768,12845]],[[512851,677571],[12982,-27788]],[[525833,649783],[-10004,-5991]],[[515829,643792],[-14590,15190]],[[484478,616183],[-235,833]],[[484243,617016],[293,129]],[[484536,617145],[-58,-962]],[[330585,596804],[15727,6396]],[[355482,593875],[-17365,-28132]],[[338117,565743],[-7532,31061]],[[264225,904837],[7936,15755]],[[272161,920592],[22583,-3125]],[[294744,917467],[-6615,-11294]],[[288150,904044],[-240,-147]],[[287910,903897],[-20409,-5917]],[[267501,897980],[-3276,6857]],[[281191,902412],[0,0]],[[287651,923406],[0,0]],[[287946,922044],[0,0]],[[282996,917748],[0,0]],[[253166,925871],[0,0]],[[259793,913222],[-506,-3183]],[[259287,910039],[-752,2627]],[[258535,912666],[1258,556]],[[259793,913222],[-9497,20507]],[[250296,933729],[15685,-5314]],[[265981,928415],[6180,-7823]],[[264225,904837],[-2280,2868]],[[261945,907705],[-2152,5517]],[[267290,920514],[0,0]],[[264771,892282],[2730,5698]],[[287910,903897],[1309,-804]],[[281374,873440],[-16603,18842]],[[572943,610984],[5071,-7938]],[[578014,603046],[-10938,-1652]],[[567076,601394],[5656,28859]],[[572732,630253],[211,-19269]],[[327363,849485],[16170,7795]],[[343533,857280],[10126,-13327],[-27790,-14954]],[[325869,828999],[-5774,13487]],[[724083,511744],[-17491,19640]],[[706592,531384],[4578,17972]],[[737878,531067],[29741,3523]],[[767619,534590],[11733,-39576]],[[779352,495014],[-25246,-14517]],[[754106,480497],[-17608,6129],[-12415,25118]],[[493167,928290],[-11364,12598]],[[481803,940888],[-722,5404]],[[481081,946292],[22974,18401]],[[504055,964693],[-10888,-36403]],[[482203,913829],[1040,569]],[[483243,914398],[-1040,-569]],[[215868,798217],[3523,1659]],[[219391,799876],[13127,-9231]],[[236288,772923],[-12945,-15752]],[[191821,725376],[-8613,-4104]],[[183208,721272],[876,7877]],[[184084,729149],[-2495,30556],[34279,38512]],[[183524,712673],[0,0]],[[203127,709987],[-17341,-12338]],[[185786,697649],[-2578,23623]],[[150797,740262],[10058,-9480]],[[160855,730782],[14866,-401]],[[175721,730381],[8363,-1232]],[[185786,697649],[-8145,11566],[-23304,-13396],[1312,-22782]],[[155649,673037],[-12884,-18499]],[[142765,654538],[-10353,10659],[-16091,59761]],[[116321,724958],[12566,-8721],[21910,24025]],[[145200,682612],[0,0]],[[238452,767530],[11194,-18512]],[[246386,723117],[-17083,8504]],[[423232,503474],[0,0]],[[389124,478178],[-799,8167]],[[388325,486345],[11608,11426],[17593,-15558]],[[423232,503474],[10380,17929]],[[433612,521403],[2658,-2471]],[[436270,518932],[14482,-10168]],[[450752,508764],[-13567,-18151]],[[437185,490613],[3312,-19445]],[[420089,480689],[3143,22785]],[[388325,486345],[-14466,18071],[8400,16512]],[[404241,533319],[26630,-11540]],[[430871,521779],[2741,-376]],[[380190,481012],[-34324,13346],[-6794,18773]],[[339072,513131],[26848,22845]],[[365920,535976],[13478,4694]],[[362052,591025],[-3357,-48113],[7225,-6936]],[[339072,513131],[-4388,7781]],[[334684,520912],[1972,18102]],[[336656,539014],[1461,26729]],[[355889,578036],[0,0]],[[310126,463414],[7320,2815]],[[317446,466229],[-955,3086]],[[316491,469315],[-3442,-633]],[[313049,468682],[14682,11393]],[[327731,480075],[2258,-9827]],[[329989,470248],[-6315,-19672]],[[323674,450576],[-14988,9135]],[[308686,459711],[1440,3703]],[[316491,469315],[955,-3086]],[[310126,463414],[-5155,-3882]],[[304971,459532],[-1348,2771]],[[303623,462303],[9426,6379]],[[178386,878779],[2934,-13017]],[[148967,867442],[29419,11337]],[[91636,804313],[0,0]],[[102263,807201],[10735,-30767]],[[112998,776434],[-9302,-19678]],[[103696,756756],[-9724,14063]],[[93972,770819],[-9491,11041]],[[84481,781860],[17782,25341]],[[488570,311963],[-9936,-11743]],[[472594,311873],[-12735,14176]],[[459859,326049],[-617,1922]],[[464414,343665],[34282,9924]],[[534899,150953],[21742,-3709]],[[554646,132571],[-5571,-24822]],[[549075,107749],[5473,-2836]],[[549422,102959],[-6977,-4649]],[[544852,116485],[0,0]],[[534221,50406],[5353,32737]],[[552531,81975],[3465,-2857]],[[555996,79118],[5163,-12298]],[[671714,364133],[22871,25732]],[[694585,389865],[20918,-72],[12072,-24376]],[[727575,365417],[-17151,-22567],[3444,-18226]],[[713868,324624],[-66,-361]],[[708062,275263],[-18807,20379]],[[702456,274323],[0,0]],[[663663,378015],[26119,20734]],[[689782,398749],[4803,-8884]],[[644666,380745],[0,0]],[[614494,263411],[-9488,36463],[4842,20864]],[[609848,320738],[25997,39928],[-7770,12331]],[[628075,372997],[-1954,4138]],[[626121,377135],[14072,1369]],[[640193,378504],[13927,-7986]],[[645124,293645],[-2649,-18536]],[[642475,275109],[-13182,-12291]],[[629293,262818],[-14799,593]],[[569162,447702],[-9670,14330],[7560,28930],[22642,4327]],[[589694,495289],[-391,-3267]],[[589303,492022],[5205,-12952]],[[594508,479070],[-25346,-31368]],[[670634,236403],[-8579,-24725]],[[616743,194358],[-8301,21014]],[[608442,215372],[32279,12509]],[[640721,227881],[29913,8522]],[[275996,982410],[-53,9284]],[[275943,991694],[37025,-1853]],[[314118,989779],[2247,-129]],[[319766,972865],[-8411,-13444]],[[311355,959421],[-2082,-2853]],[[309273,956568],[941,-8021]],[[310214,948547],[-7259,-4187]],[[302955,944360],[-6157,-729]],[[296798,943631],[-4893,12476]],[[291905,956107],[-15909,26303]],[[682719,548595],[2433,-7229]],[[685152,541366],[-27928,-11287],[-15804,20755]],[[641420,550834],[12729,23771]],[[654149,574605],[28570,-26010]],[[654149,574605],[8177,11369]],[[662326,585974],[10047,4037]],[[672373,590011],[11227,-3449]],[[683600,586562],[-645,-9691]],[[682955,576871],[-236,-28276]],[[752354,705764],[5720,16938]],[[774019,711550],[17784,-21088]],[[791803,690462],[2501,-48673]],[[794304,641789],[-6820,5613]],[[787484,647402],[-40129,25962]],[[747355,673364],[4999,32400]],[[816622,697640],[-1806,-16848],[-21754,15022]],[[793062,695814],[-245,19810],[22886,-647],[919,-17337]],[[803744,717773],[0,0]],[[839923,704090],[-2928,2060]],[[561514,383128],[-5088,-4071]],[[549569,398050],[-3513,31359]],[[546056,429409],[9561,13058]],[[555617,442467],[11996,-1667]],[[567613,440800],[10699,-19217]],[[578312,421583],[14841,-12926]],[[593153,408657],[-9008,-14561]],[[584145,394096],[-22631,-10968]],[[248394,611349],[20679,-9119]],[[269073,602230],[6350,-15668],[-17412,-22173]],[[215870,559060],[-45651,40937]],[[183909,620093],[33377,-16551],[4951,9543]],[[222237,613085],[26157,-1736]],[[234895,520762],[-3360,14061]],[[252798,555488],[8683,-23285]],[[261481,532203],[-26586,-11441]],[[234318,878603],[-5661,99]],[[228657,878702],[-21750,15301]],[[206907,894003],[-491,-72]],[[207737,899037],[12662,-2835]],[[463868,239632],[5162,-26461]],[[469030,213171],[-11375,-8702]],[[447242,201914],[-2109,-628]],[[445133,201286],[-9667,11335]],[[435466,212621],[-29222,-9755]],[[406244,202866],[-798,20457]],[[405446,223323],[39979,19338]],[[852361,577622],[22013,14044]],[[874374,591666],[22311,-30966],[210,-28200]],[[896895,532500],[-11071,-30936]],[[873720,511515],[-7508,13863]],[[901440,613990],[-229,6079]],[[901211,620069],[-1636,961]],[[899575,621030],[-6411,1979]],[[893164,623009],[-1079,8186]],[[892085,631195],[-2379,6363]],[[889706,637558],[2991,3525]],[[900069,656152],[31491,4338]],[[931560,660490],[28338,-36227]],[[938986,587983],[-37546,26007]],[[900813,536545],[0,0]],[[903489,540295],[10561,-18012]],[[910367,509295],[-6541,-12710]],[[896895,532500],[6594,7795]],[[901211,620069],[-1636,961]],[[899575,621030],[-6411,1979]],[[893164,623009],[-34504,-5910],[14404,-22733]],[[873064,594366],[1310,-2700]],[[836088,606595],[12141,24376]],[[889706,637558],[2379,-6363]],[[585287,616034],[-12344,-5050]],[[572732,630253],[-1354,1218]],[[571378,631471],[413,43645]],[[571791,675116],[43917,-5945]],[[538976,763243],[-4249,-19798]],[[522069,751404],[-7231,10377]],[[514838,761781],[24138,1462]],[[318207,745055],[8420,5139]],[[782235,821783],[4412,-7479]],[[786647,814304],[-4412,7479]],[[104065,831538],[564,-3347]],[[110499,823612],[-3634,-9823]],[[106865,813789],[-4602,-6588]],[[84481,781860],[-3923,6846]],[[80558,788706],[-16582,23788],[5120,18476]],[[69096,830970],[35589,4710]],[[588941,431248],[0,0]],[[595570,437000],[11996,15839]],[[607566,452839],[8052,-8755]],[[615618,444084],[3623,-16938]],[[619241,427146],[-23671,9854]],[[178432,897351],[-46,-18572]],[[142404,883463],[11617,38221]],[[121015,907442],[-12053,-900],[15780,31722]],[[119160,876592],[-11427,21327]],[[107733,897919],[13282,9523]],[[121015,907442],[0,0]],[[107733,897919],[-14307,-6130]],[[93426,891789],[-7704,37933],[9234,20129]],[[94956,949851],[25491,2722]],[[497938,646345],[-417,1777]],[[497521,648122],[3718,10860]],[[515829,643792],[-13161,-12796]],[[502668,630996],[-9545,3030]],[[489206,635210],[8732,11135]],[[497938,646345],[-417,1777]],[[483487,615717],[-122,418]],[[483365,616135],[122,-418]],[[236269,944539],[39727,37871]],[[291905,956107],[-15376,-17604]],[[276529,938503],[-10548,-10088]],[[250296,933729],[-12217,4092]],[[280639,974939],[0,0]],[[296798,943631],[-20269,-5128]],[[336059,909710],[-2401,-293]],[[333658,909417],[2401,293]],[[316712,928603],[200,206]],[[595279,615790],[5990,-1313]],[[605722,610711],[3119,-3216]],[[608841,607495],[14491,-27974],[-1744,-33202]],[[621588,546319],[-6424,-8027]],[[615164,538292],[-13854,18946]],[[601310,557238],[-899,41006],[-22397,4802]],[[767619,534590],[15032,484]],[[782651,535074],[33003,-36177]],[[814002,489871],[-34650,5143]],[[410654,922921],[-17278,-36274]],[[393376,886647],[-5246,54038]],[[388130,940685],[57,1091]],[[388187,941776],[22467,-18855]],[[177492,640475],[10681,-3679]],[[188173,636796],[-6139,-10431]],[[155649,673037],[21826,-32562]],[[157965,622207],[-15200,32331]],[[156873,804941],[31370,7111]],[[188243,812052],[27625,-13835]],[[175721,730381],[-5229,36017],[-14623,8764],[1004,29779]],[[345640,430694],[0,0]],[[116321,724958],[-9689,17757]],[[106632,742715],[36063,15272]],[[142695,757987],[8102,-17725]],[[160855,730782],[-14832,45614]],[[146023,776396],[-14297,24197]],[[131726,800593],[16158,23380]],[[147884,823973],[8989,-19032]],[[141800,786277],[0,0]],[[489485,65895],[21106,-41829]],[[515327,13816],[-10380,-11587],[-39621,23874],[-8161,39230],[2620,34313]],[[502663,507862],[-6235,12214]],[[496428,520076],[5046,19246],[22604,11710]],[[524078,551032],[25310,-5891]],[[549388,545141],[14163,-4931]],[[563551,540210],[5196,-3058]],[[568747,537152],[4893,-15011]],[[573640,522141],[-2,-110]],[[573638,522031],[-18320,-8165],[-16693,-30148]],[[538625,483718],[-2306,2532]],[[708266,232349],[6801,-3268]],[[715067,229081],[11291,-7248]],[[726358,221833],[-5206,-15802]],[[702799,190015],[-2971,-5083]],[[699828,184932],[-2898,44947]],[[413445,984076],[3983,-23508]],[[417428,960568],[-687,-2163]],[[416741,958405],[-6656,-1622]],[[410085,956783],[-21898,-15007]],[[388130,940685],[-18338,28576]],[[362901,987041],[50544,-2965]],[[733124,785092],[16686,-25569]],[[703970,765417],[2793,5456]],[[706763,770873],[3607,29458]],[[710370,800331],[22754,-15239]],[[603018,747482],[-8432,18905],[18993,29195]],[[613579,795582],[9514,-9095]],[[623093,786487],[14602,-54143]],[[636496,722552],[-13493,-1126]],[[621788,720882],[-18770,26600]],[[557311,227297],[25189,-2726],[4590,20107]],[[587090,244678],[1104,-16473]],[[588194,228205],[13036,-45699],[22297,-38155]],[[616701,127612],[-9563,7674]],[[580998,223147],[0,0]],[[531708,242968],[871,-1063]],[[546574,324634],[-905,-40309],[-18378,-15284],[524,-26738]],[[516756,263611],[-1466,24457]],[[520706,315328],[0,0]],[[669763,702847],[3388,2593]],[[673151,705440],[2172,3204]],[[675323,708644],[9913,-12630]],[[685236,696014],[10139,-25907],[-12769,-25196]],[[682606,644911],[-19746,25436]],[[673151,705440],[2172,3204]],[[833857,708198],[-17235,-10558]],[[793062,695814],[-1259,-5352]],[[795776,769631],[643,1712]],[[584145,394096],[4802,-20657]],[[588947,373439],[3452,-51454]],[[592399,321985],[-13477,-341]],[[578922,321644],[-16327,10167]],[[562595,331811],[9981,35567],[-11062,15750]],[[308069,586984],[22516,9820]],[[336656,539014],[-28243,5110]],[[308413,544124],[-10165,36144],[9821,6716]],[[782651,535074],[-8937,22550]],[[773714,557624],[28792,-10374],[35818,7470]],[[231842,839330],[19292,25495]],[[251134,864825],[14921,-28951]],[[219391,799876],[-836,14334]],[[218555,814210],[13287,25120]],[[433972,259712],[3681,14376]],[[444073,254297],[-10101,5415]],[[952208,551817],[8548,-339]],[[960756,551478],[-21150,-19854]],[[919374,505560],[-10020,-15685]],[[901440,613990],[-2678,-16997],[-25698,-2627]],[[584066,743368],[18952,4114]],[[608308,700965],[-29060,9261],[4818,33142]],[[578341,832828],[-18540,-37049],[484,-26448]],[[560285,769331],[-21309,-6088]],[[514838,761781],[-193,16915]],[[514645,778696],[-456,22999]],[[316348,804100],[9273,-5728]],[[325621,798372],[1255,-17462],[23707,-5813],[-14217,-21877]],[[303845,728000],[-15515,23718]],[[288330,751718],[15427,53873]],[[303757,805591],[12591,-1491]],[[283942,798558],[19815,7033]],[[288330,751718],[-17605,-9456]],[[259555,890649],[5216,1633]],[[303408,850001],[-28120,-26843]],[[251134,864825],[-4710,5094]],[[254376,888416],[5179,2233]],[[259555,890649],[0,0]],[[325869,828999],[-9521,-24899]],[[310420,822623],[0,0]],[[659745,634691],[485,-31909],[12143,-12771]],[[662326,585974],[-17296,22924],[-4914,38265]],[[641420,550834],[-681,-281]],[[640739,550553],[-13933,25949],[2572,23668],[-20537,7325]],[[370156,643260],[0,0]],[[372816,642900],[34911,-2538]],[[407727,640362],[-9247,-13966],[17965,-71134]],[[416445,555262],[14426,-33483]],[[832701,626056],[0,0]],[[834181,617619],[-7636,11876]],[[805513,607212],[-11209,34577]],[[364653,746535],[27926,4446]],[[392579,750981],[-5188,-39214]],[[387391,711767],[-23670,-28356],[-1162,-26676]],[[362559,656735],[-21853,16318]],[[340706,673053],[8857,4040],[-24601,30054]],[[392579,750981],[11585,3091]],[[404164,754072],[13608,-42024]],[[417772,712048],[5145,-17556]],[[422917,694492],[-2524,-694]],[[420393,693798],[-21455,-3702]],[[398938,690096],[-11547,21671]],[[93426,891789],[1688,-21504]],[[95114,870285],[-12281,10314]],[[82833,880599],[-5026,265]],[[71481,892474],[-1732,47646]],[[69749,940120],[25207,9731]],[[92878,845770],[0,0]],[[437185,490613],[12874,-9417],[37946,1662]],[[488953,480600],[-7452,-34489]],[[481501,446111],[-5112,-240]],[[476389,445871],[-30177,6556]],[[518536,433528],[-5012,-16944]],[[513524,416584],[-16243,22180]],[[497281,438764],[21255,-5236]],[[501796,620998],[0,0]],[[502668,630996],[-4433,-14378]],[[498235,616618],[-1750,-5]],[[496485,616613],[-4065,3800]],[[497459,615676],[0,0]],[[484478,616183],[-991,-466]],[[483365,616135],[-123,414]],[[483242,616549],[1001,467]],[[496485,616613],[-2636,-10425]],[[493849,606188],[-8437,13353]],[[525833,649783],[9721,245]],[[535554,650028],[12292,-11342]],[[547846,638686],[-12461,-19647]],[[535385,619039],[-22856,-5675]],[[512529,613364],[-14294,3254]],[[329904,886330],[26509,8226]],[[356413,894556],[605,4]],[[357018,894560],[9834,2012]],[[366852,896572],[27732,-14858]],[[394584,881714],[-6203,-7127]],[[388381,874587],[-44848,-17307]],[[325348,872798],[4556,13532]],[[355532,865316],[0,0]],[[457764,918560],[24039,22328]],[[493167,928290],[-9924,-13892]],[[482203,913829],[-27615,-12141]],[[454588,901688],[3176,16872]],[[457764,918560],[0,0]],[[304137,500568],[192,-13913]],[[279088,470775],[-7601,10303]],[[271487,481078],[14594,34179]],[[286081,515257],[9415,6293]],[[295496,521550],[8641,-20982]],[[382297,423688],[-2267,3518]],[[415244,427705],[1391,-17644]],[[459859,326049],[-21058,-6864]],[[438801,319185],[-19365,18338]],[[557674,108893],[-587,4098]],[[557830,115137],[-8755,-7388]],[[560710,95366],[-4714,-16248]],[[461003,583477],[26144,-3306]],[[487147,580171],[9650,-10133]],[[496797,570038],[4196,-3760]],[[500993,566278],[-46432,-24628]],[[454561,541650],[-5284,12322]],[[449277,553972],[7019,26185]],[[456296,580157],[4707,3320]],[[673971,243798],[0,0]],[[690411,231799],[-30588,28971]],[[666659,275158],[3642,-2921]],[[671444,272453],[15852,-16897]],[[687296,255556],[5267,-3899]],[[699828,184932],[-42367,-21573]],[[670634,236403],[-9175,18576]],[[687296,255556],[10759,5648]],[[698055,261204],[7459,8041]],[[705514,269245],[6589,-19498]],[[712103,249747],[-7528,-443]],[[685485,281879],[858,-1486]],[[686343,280393],[6307,-12609]],[[692650,267784],[5405,-6580]],[[754870,258033],[-15917,-14913]],[[729104,266527],[9802,14942]],[[738906,281469],[15964,-23436]],[[706030,238788],[0,0]],[[710365,235822],[348,187]],[[710713,236009],[-348,-187]],[[310214,948547],[22290,-14319]],[[332504,934228],[4120,-21761]],[[336624,912467],[-565,-2757]],[[333658,909417],[-4425,284]],[[329233,909701],[-12551,4417]],[[316682,914118],[-1822,-45]],[[314860,914073],[-16636,6386]],[[298224,920459],[1113,791]],[[299337,921250],[2,2623]],[[299339,923873],[3616,20487]],[[494591,804687],[2644,-15037]],[[497235,789650],[-11468,-16020],[-50596,-13467]],[[435171,760163],[-7334,28896]],[[427837,789059],[-685,6802]],[[427152,795861],[20101,5087],[5150,21995],[21827,-9402]],[[623093,786487],[38667,3615]],[[661760,790102],[320,-1976]],[[662080,788126],[4374,-28405],[-10221,-31396]],[[695442,825440],[14928,-25109]],[[706763,770873],[-17132,18652],[-27551,-1399]],[[661760,790102],[-1552,23330],[-16966,1557]],[[661294,822573],[19275,-10542],[14873,13409]],[[682955,576871],[22334,-8074]],[[705289,568797],[4011,-10590]],[[706592,531384],[-15122,-8934]],[[691470,522450],[-6318,18916]],[[703037,601060],[1597,-17925]],[[704634,583135],[655,-14338]],[[683600,586562],[19437,14498]],[[700857,616127],[0,0]],[[700857,616127],[11454,5553]],[[712311,621680],[9563,-7152]],[[721874,614528],[1003,-21459]],[[722877,593069],[-18243,-9934]],[[703037,601060],[-2180,15067]],[[562519,331856],[76,-45]],[[578922,321644],[-1536,-68693],[9704,-8273]],[[593153,408657],[3789,-17121],[29179,-14401]],[[628075,372997],[-12754,-13815],[-26374,14257]],[[609848,320738],[-16988,877]],[[592860,321615],[-461,370]],[[474455,696185],[-7296,-26182]],[[467159,670003],[-14538,2742]],[[438236,681722],[-13673,10763]],[[424563,692485],[10907,27309]],[[435470,719794],[-299,40369]],[[497235,789650],[17410,-10954]],[[417772,712048],[17698,7746]],[[424563,692485],[-781,664]],[[423782,693149],[-865,1343]],[[404164,754072],[-2503,19216]],[[401661,773288],[111,24411],[26065,-8640]],[[781687,643347],[5797,4055]],[[805387,598251],[-13149,-26825]],[[792238,571426],[-22951,18981]],[[769287,590407],[-124,2356]],[[769163,592763],[3911,20162]],[[773714,557624],[18524,13802]],[[769163,592763],[-32061,25630]],[[759148,623798],[10015,-31035]],[[265862,992087],[10081,-393]],[[445133,201286],[-9667,11335]],[[469030,213171],[667,-27001]],[[454836,162697],[5471,33313]],[[903489,540295],[43855,16736]],[[959574,560885],[34834,19115]],[[994408,580000],[5591,-7269],[-39243,-21253]],[[542337,667903],[0,0]],[[552524,722927],[19267,-47811]],[[571378,631471],[-23532,7215]],[[535554,650028],[14065,21495],[-19947,28275]],[[568329,754794],[-8044,14537]],[[596702,843470],[16877,-47888]],[[584066,743368],[-7895,7305]],[[576171,750673],[-7842,4121]],[[682606,644911],[29705,-23231]],[[470293,604061],[-1077,-3776]],[[469216,600285],[-8213,-16808]],[[456296,580157],[-6391,20642],[13360,16807]],[[469216,600285],[14420,-8680]],[[483636,591605],[3511,-11434]],[[417992,596917],[0,0]],[[407727,640362],[12944,-2011]],[[420671,638351],[-11624,-11898],[12881,-36450]],[[421928,590003],[-671,-23422]],[[421257,566581],[-4812,-11319]],[[423782,693149],[-3389,649]],[[82833,880599],[-12024,-34748]],[[61941,936844],[7808,3276]],[[60247,888582],[1694,48262]],[[594508,479070],[13058,-26231]],[[595570,437000],[-17258,-15417]],[[567613,440800],[1549,6902]],[[476389,445871],[-3820,-24336]],[[481501,446111],[15780,-7347]],[[513524,416584],[-326,-30032]],[[513198,386552],[-38869,32776]],[[521132,460412],[0,0]],[[111741,868663],[0,0]],[[122636,871194],[-10895,-2531]],[[111741,868663],[-13878,-1879]],[[97863,866784],[-2749,3501]],[[483636,591605],[2404,5004]],[[486040,596609],[7809,9579]],[[512529,613364],[-15732,-43326]],[[567076,601394],[1671,-64242]],[[563551,540210],[-9318,36234],[-21730,717]],[[532503,577161],[-7075,25736],[9957,16142]],[[532503,577161],[-9313,-23716],[26198,-8304]],[[524078,551032],[-23085,15246]],[[302228,882776],[-5280,36692]],[[296948,919468],[1276,991]],[[314860,914073],[1822,45]],[[329233,909701],[671,-23371]],[[261945,907705],[-2658,2334]],[[299337,921250],[2,2623]],[[263668,637952],[-360,-11903]],[[263308,626049],[-233,-933]],[[263075,625116],[593,12836]],[[222237,613085],[-8583,24943]],[[213654,638028],[4908,20964]],[[218562,658992],[12086,5512],[17746,-53155]],[[303623,462303],[-6,24]],[[304137,500568],[13339,-2846]],[[317476,497722],[4361,-12342]],[[321837,485380],[5894,-5305]],[[299505,440344],[-2382,8343]],[[304971,459532],[3715,179]],[[323674,450576],[-7077,-26931]],[[402135,329309],[314,-28298],[-14925,1760]],[[387524,302771],[-44403,37339],[-10903,25683]],[[395743,263246],[43058,55939]],[[433972,259712],[-38229,3534]],[[194007,891469],[-526,-13073]],[[450752,508764],[19923,18106],[25753,-6794]],[[845061,337763],[-14263,-32296],[-37878,-4194]],[[792920,301273],[-17856,14786],[4022,29272]],[[715067,229081],[-79,6049]],[[737359,234094],[-533,-1046]],[[736826,233048],[-10468,-11215]],[[640721,227881],[-20938,26941],[9510,7996]],[[642475,275109],[8818,-11447]],[[715137,239424],[-4424,-3415]],[[710365,235822],[-3633,-1590]],[[712103,249747],[2790,-3181]],[[682464,296704],[0,0]],[[338902,937436],[-6398,-3208]],[[309273,956568],[2082,2853]],[[427152,795861],[-15336,55989],[-16580,-15908]],[[395236,835942],[-5042,9434]],[[390194,845376],[4974,17676]],[[395168,863052],[32569,13236]],[[460359,875833],[21561,-8267]],[[370926,798206],[31276,6777],[-6966,30959]],[[401661,773288],[-14874,-692],[-15861,25610]],[[395168,863052],[-2194,6495]],[[392974,869547],[-4593,5040]],[[394584,881714],[-1208,4933]],[[410654,922921],[5762,-2203]],[[416416,920718],[14585,-21564]],[[694993,872008],[17820,-582]],[[712813,871426],[11578,-35434],[19586,-25006]],[[743977,810986],[-10853,-25894]],[[695442,825440],[-8146,28827],[7697,17741]],[[704334,721671],[-9314,-26939]],[[695020,694732],[-9784,1282]],[[592860,321615],[-5056,-45114],[26186,-15166]],[[613990,261335],[-3368,-20219]],[[610622,241116],[-22428,-12911]],[[610622,241116],[-2180,-25744]],[[614494,263411],[-504,-2076]],[[695020,694732],[20607,-17407]],[[715627,677325],[16856,-12397]],[[729484,612236],[-7610,2292]],[[308069,586984],[-14196,28546]],[[293873,615530],[-5773,7423]],[[288100,622953],[17638,12594]],[[305738,635547],[30452,40690]],[[336190,676237],[4516,-3184]],[[362559,656735],[-1619,-17449]],[[739237,593012],[-16360,57]],[[769287,590407],[-9950,-12618],[-20100,15223]],[[739237,593012],[0,0]],[[228657,878702],[-5306,-12211]],[[219628,857528],[-5637,-10546]],[[202850,877845],[-1406,10105]],[[205440,891851],[93,-438]],[[206955,892379],[-48,1624]],[[224521,866706],[0,0]],[[227932,876466],[0,0]],[[224572,867962],[0,0]],[[222085,854965],[9757,-15635]],[[218555,814210],[-7518,13997]],[[293873,615530],[-24800,-13300]],[[248394,611349],[14681,13767]],[[263308,626049],[24792,-3096]],[[188173,636796],[25481,1232]],[[283322,694030],[9788,-12297]],[[293110,681733],[12628,-46186]],[[263668,637952],[-238,31511],[19892,24567]],[[483320,197176],[-4025,31934],[35393,9020]],[[491809,275328],[22879,-37198]],[[981891,596074],[12517,-16074]],[[568329,754794],[7842,-4121]],[[499937,925101],[0,0]],[[509182,956341],[25875,-44288]],[[516934,914974],[-7752,41367]],[[449277,553972],[-28020,12609]],[[421928,590003],[40510,35177]],[[448514,606761],[0,0]],[[447278,606568],[0,0]],[[454561,541650],[-18291,-22718]],[[787044,811948],[-397,2356]],[[782235,821783],[-7058,36817]],[[775177,858600],[36993,-45496]],[[809968,807314],[-22924,4634]],[[293110,681733],[11237,31520]],[[304347,713253],[4429,3363]],[[312648,703987],[-1778,-27174],[25320,-576]],[[80558,788706],[-26249,-3311]],[[54309,785395],[-16581,23548],[-35375,23638],[-2233,13716]],[[120,846297],[25161,12736]],[[25281,859033],[7308,-2977]],[[68305,841649],[791,-10679]],[[97863,866784],[6968,-29973]],[[25281,859033],[-15435,14757]],[[9846,873790],[52095,63054]],[[513039,385407],[159,1145]],[[518536,433528],[27520,-4119]],[[538625,483718],[16992,-41251]],[[637574,391245],[-18333,35901]],[[615618,444084],[35896,-1092]],[[651514,442992],[-13940,-51747]],[[483215,624965],[-6966,-540]],[[468058,645914],[-6867,13875]],[[467159,670003],[32924,-5277]],[[486040,596609],[-6335,18528]],[[484536,617145],[-1294,-596]],[[296948,919468],[-2204,-2001]],[[258535,912666],[-13117,6219]],[[601310,557238],[-27670,-35097]],[[754106,480497],[-4621,-31262]],[[708152,466436],[4309,47187],[11622,-1879]],[[417428,960568],[-687,-2163]],[[416741,958405],[-2362,-3909]],[[414379,954496],[-1355,1252]],[[413024,955748],[-2939,1035]],[[413445,984076],[69362,-4933],[-5121,-25823]],[[477686,953320],[-45865,539],[-16268,-26822]],[[415553,927037],[4490,17452]],[[420043,944489],[104,2300]],[[420147,946789],[-2719,13779]],[[431861,957192],[0,0]],[[423348,967033],[0,0]],[[420043,944489],[104,2300]],[[414379,954496],[-1355,1252]],[[420147,946789],[-5768,7707]],[[416416,920718],[-863,6319]],[[477686,953320],[3395,-7028]],[[454588,901688],[-1476,-4103]],[[212829,706134],[17443,-19993]],[[230272,686141],[1478,-8459]],[[231750,677682],[-13188,-18690]],[[321837,485380],[-3545,13288]],[[318292,498668],[16392,22244]],[[370388,465013],[-40399,5235]],[[317476,497722],[816,946]],[[395743,263246],[-149,-59]],[[395594,263187],[-8070,39584]],[[139409,775698],[3286,-17711]],[[106632,742715],[-2936,14041]],[[112998,776434],[26411,-736]],[[147884,823973],[10011,12307]],[[160703,834028],[27540,-21976]],[[171777,816470],[0,0]],[[171983,817524],[0,0]],[[106865,813789],[24861,-13196]],[[146023,776396],[-6614,-698]],[[125392,858631],[45,-2768]],[[136819,836393],[-18994,-7036]],[[689645,398899],[137,-150]],[[640193,378504],[-2619,12741]],[[651514,442992],[2768,-332]],[[654282,442660],[35363,-43761]],[[654282,442660],[5946,3792]],[[660228,446452],[16369,13257]],[[676597,459709],[29417,-903]],[[706014,458806],[-2200,-45059]],[[703814,413747],[-14169,-14848]],[[573638,522031],[16056,-26742]],[[738906,281469],[8060,8312]],[[746966,289781],[24599,51595]],[[792920,301273],[-7201,-26480],[-25134,-18914]],[[760585,255879],[-5715,2154]],[[760585,255879],[-23759,-22831]],[[366852,896572],[-9834,-2012]],[[356413,894556],[2747,21096],[-22536,-3185]],[[493167,928290],[23963,-14528]],[[621210,513854],[-6046,24438]],[[621588,546319],[19151,4234]],[[691470,522450],[-14873,-62741]],[[660228,446452],[-17520,46510],[-21498,20892]],[[589303,492022],[20365,-549],[11542,22381]],[[715627,677325],[21900,30091],[14827,-1652]],[[747355,673364],[-9315,-6574]],[[271487,481078],[-30712,20658],[-5880,19026]],[[261481,532203],[366,-24413],[24234,7467]],[[751604,404825],[-26285,35003]],[[512851,677571],[1810,22701]],[[304347,713253],[-28002,15034]],[[325621,798372],[45305,-166]],[[420671,638351],[3717,-666]],[[424388,637685],[34761,-9677]],[[399039,658539],[-101,31557]],[[437741,680977],[-21676,2801],[-17026,-25239]],[[424388,637685],[9363,11513]],[[787044,811948],[-5657,-20828]],[[743977,810986],[3088,60284]],[[747065,871270],[28112,-12670]],[[712813,871426],[34252,-156]],[[392974,869547],[-2780,-24171]],[[504055,964693],[5127,-8352]],[[257952,714308],[-27680,-28167]],[[242986,668388],[0,0]],[[276354,699117],[-44604,-21435]],[[277443,697069],[5879,-3039]],[[295496,521550],[12917,22574]],[[405446,223323],[-9852,39864]],[[93972,770819],[-27531,-929],[-12132,15505]],[[617854,126748],[-14650,-36392],[-40572,-26286]],[[742437,366280],[0,0]],[[703814,413747],[43173,-17533]],[[748219,376825],[-20644,-11408]],[[705514,269245],[2882,5369]],[[716048,295388],[30918,-5607]],[[713868,324624],[12878,1030],[19356,33785]],[[692650,267784],[-6307,12609]],[[659369,873120],[35624,-1112]],[[433889,155295],[-31275,31698],[3630,15873]],[[908251,690064],[23309,-29574]],[[407727,640362],[-8688,18177]],[[120,846297],[9726,27493]]],"transform":{"scale":[0.000004806745806745809,0.0000031809741809741803],"translate":[-83.353928,32.034569]}}