[{"zip":"99501","county":"Anchorage"},{"zip":"99502","county":"Anchorage"},{"zip":"99503","county":"Anchorage"},{"zip":"99504","county":"Anchorage"},{"zip":"99505","county":"Fort Richardson"},{"zip":"99506","county":"Elmendorf Afb"},{"zip":"99507","county":"Anchorage"},{"zip":"99508","county":"Anchorage"},{"zip":"99509","county":"Anchorage"},{"zip":"99510","county":"Anchorage"},{"zip":"99511","county":"Anchorage"},{"zip":"99513","county":"Anchorage"},{"zip":"99514","county":"Anchorage"},{"zip":"99515","county":"Anchorage"},{"zip":"99516","county":"Anchorage"},{"zip":"99517","county":"Anchorage"},{"zip":"99518","county":"Anchorage"},{"zip":"99519","county":"Anchorage"},{"zip":"99520","county":"Anchorage"},{"zip":"99521","county":"Anchorage"},{"zip":"99522","county":"Anchorage"},{"zip":"99523","county":"Anchorage"},{"zip":"99524","county":"Anchorage"},{"zip":"99529","county":"Anchorage"},{"zip":"99530","county":"Anchorage"},{"zip":"99540","county":"Indian"},{"zip":"99545","county":"Kongiganak"},{"zip":"99546","county":"Adak"},{"zip":"99547","county":"Atka"},{"zip":"99548","county":"Chignik Lake"},{"zip":"99549","county":"Port Heiden"},{"zip":"99550","county":"Port Lions"},{"zip":"99551","county":"Akiachak"},{"zip":"99552","county":"Akiak"},{"zip":"99553","county":"Akutan"},{"zip":"99554","county":"Alakanuk"},{"zip":"99555","county":"Aleknagik"},{"zip":"99556","county":"Anchor Point"},{"zip":"99557","county":"Aniak"},{"zip":"99558","county":"Anvik"},{"zip":"99559","county":"Bethel"},{"zip":"99561","county":"Chefornak"},{"zip":"99563","county":"Chevak"},{"zip":"99564","county":"Chignik"},{"zip":"99565","county":"Chignik Lagoon"},{"zip":"99566","county":"Chitina"},{"zip":"99567","county":"Chugiak"},{"zip":"99568","county":"Clam Gulch"},{"zip":"99569","county":"Clarks Point"},{"zip":"99571","county":"Cold Bay"},{"zip":"99572","county":"Cooper Landing"},{"zip":"99573","county":"Copper Center"},{"zip":"99574","county":"Cordova"},{"zip":"99575","county":"Crooked Creek"},{"zip":"99576","county":"Dillingham"},{"zip":"99577","county":"Eagle River"},{"zip":"99578","county":"Eek"},{"zip":"99579","county":"Egegik"},{"zip":"99580","county":"Ekwok"},{"zip":"99581","county":"Emmonak"},{"zip":"99583","county":"False Pass"},{"zip":"99585","county":"Marshall"},{"zip":"99586","county":"Gakona"},{"zip":"99587","county":"Girdwood"},{"zip":"99588","county":"Glennallen"},{"zip":"99589","county":"Goodnews Bay"},{"zip":"99590","county":"Grayling"},{"zip":"99591","county":"Saint George Island"},{"zip":"99599","county":"Anchorage"},{"zip":"99602","county":"Holy Cross"},{"zip":"99603","county":"Homer"},{"zip":"99604","county":"Hooper Bay"},{"zip":"99605","county":"Hope"},{"zip":"99606","county":"Iliamna"},{"zip":"99607","county":"Kalskag"},{"zip":"99608","county":"Karluk"},{"zip":"99609","county":"Kasigluk"},{"zip":"99610","county":"Kasilof"},{"zip":"99611","county":"Kenai"},{"zip":"99612","county":"King Cove"},{"zip":"99613","county":"King Salmon"},{"zip":"99614","county":"Kipnuk"},{"zip":"99615","county":"Kodiak"},{"zip":"99619","county":"Kodiak"},{"zip":"99620","county":"Kotlik"},{"zip":"99621","county":"Kwethluk"},{"zip":"99622","county":"Kwigillingok"},{"zip":"99624","county":"Larsen Bay"},{"zip":"99625","county":"Levelock"},{"zip":"99626","county":"Lower Kalskag"},{"zip":"99627","county":"Mc Grath"},{"zip":"99628","county":"Manokotak"},{"zip":"99629","county":"Wasilla"},{"zip":"99630","county":"Mekoryuk"},{"zip":"99631","county":"Moose Pass"},{"zip":"99632","county":"Mountain Village"},{"zip":"99633","county":"Naknek"},{"zip":"99634","county":"Napakiak"},{"zip":"99635","county":"Nikiski"},{"zip":"99636","county":"New Stuyahok"},{"zip":"99637","county":"Toksook Bay"},{"zip":"99638","county":"Nikolski"},{"zip":"99639","county":"Ninilchik"},{"zip":"99640","county":"Nondalton"},{"zip":"99641","county":"Nunapitchuk"},{"zip":"99643","county":"Old Harbor"},{"zip":"99644","county":"Ouzinkie"},{"zip":"99645","county":"Palmer"},{"zip":"99647","county":"Pedro Bay"},{"zip":"99648","county":"Perryville"},{"zip":"99649","county":"Pilot Point"},{"zip":"99650","county":"Pilot Station"},{"zip":"99651","county":"Platinum"},{"zip":"99652","county":"Big Lake"},{"zip":"99653","county":"Port Alsworth"},{"zip":"99654","county":"Wasilla"},{"zip":"99655","county":"Quinhagak"},{"zip":"99656","county":"Red Devil"},{"zip":"99657","county":"Russian Mission"},{"zip":"99658","county":"Saint Marys"},{"zip":"99659","county":"Saint Michael"},{"zip":"99660","county":"Saint Paul Island"},{"zip":"99661","county":"Sand Point"},{"zip":"99662","county":"Scammon Bay"},{"zip":"99663","county":"Seldovia"},{"zip":"99664","county":"Seward"},{"zip":"99665","county":"Shageluk"},{"zip":"99666","county":"Nunam Iqua"},{"zip":"99667","county":"Skwentna"},{"zip":"99668","county":"Sleetmute"},{"zip":"99669","county":"Soldotna"},{"zip":"99670","county":"South Naknek"},{"zip":"99671","county":"Stebbins"},{"zip":"99672","county":"Sterling"},{"zip":"99674","county":"Sutton"},{"zip":"99675","county":"Takotna"},{"zip":"99676","county":"Talkeetna"},{"zip":"99677","county":"Tatitlek"},{"zip":"99678","county":"Togiak"},{"zip":"99679","county":"Tuluksak"},{"zip":"99680","county":"Tuntutuliak"},{"zip":"99681","county":"Tununak"},{"zip":"99682","county":"Tyonek"},{"zip":"99683","county":"Trapper Creek"},{"zip":"99684","county":"Unalakleet"},{"zip":"99685","county":"Unalaska"},{"zip":"99686","county":"Valdez"},{"zip":"99687","county":"Wasilla"},{"zip":"99688","county":"Willow"},{"zip":"99689","county":"Yakutat"},{"zip":"99690","county":"Nightmute"},{"zip":"99691","county":"Nikolai"},{"zip":"99692","county":"Dutch Harbor"},{"zip":"99693","county":"Whittier"},{"zip":"99694","county":"Houston"},{"zip":"99695","county":"Anchorage"},{"zip":"99697","county":"Kodiak"},{"zip":"99701","county":"Fairbanks"},{"zip":"99702","county":"Eielson Afb"},{"zip":"99703","county":"Fort Wainwright"},{"zip":"99704","county":"Clear"},{"zip":"99705","county":"North Pole"},{"zip":"99706","county":"Fairbanks"},{"zip":"99707","county":"Fairbanks"},{"zip":"99708","county":"Fairbanks"},{"zip":"99709","county":"Fairbanks"},{"zip":"99710","county":"Fairbanks"},{"zip":"99711","county":"Fairbanks"},{"zip":"99712","county":"Fairbanks"},{"zip":"99714","county":"Salcha"},{"zip":"99716","county":"Two Rivers"},{"zip":"99720","county":"Allakaket"},{"zip":"99721","county":"Anaktuvuk Pass"},{"zip":"99722","county":"Arctic Village"},{"zip":"99723","county":"Barrow"},{"zip":"99724","county":"Beaver"},{"zip":"99725","county":"Ester"},{"zip":"99726","county":"Bettles Field"},{"zip":"99727","county":"Buckland"},{"zip":"99729","county":"Cantwell"},{"zip":"99730","county":"Central"},{"zip":"99731","county":"Fort Greely"},{"zip":"99732","county":"Chicken"},{"zip":"99733","county":"Circle"},{"zip":"99734","county":"Prudhoe Bay"},{"zip":"99736","county":"Deering"},{"zip":"99737","county":"Delta Junction"},{"zip":"99738","county":"Eagle"},{"zip":"99739","county":"Elim"},{"zip":"99740","county":"Fort Yukon"},{"zip":"99741","county":"Galena"},{"zip":"99742","county":"Gambell"},{"zip":"99743","county":"Healy"},{"zip":"99744","county":"Anderson"},{"zip":"99745","county":"Hughes"},{"zip":"99746","county":"Huslia"},{"zip":"99747","county":"Kaktovik"},{"zip":"99748","county":"Kaltag"},{"zip":"99749","county":"Kiana"},{"zip":"99750","county":"Kivalina"},{"zip":"99751","county":"Kobuk"},{"zip":"99752","county":"Kotzebue"},{"zip":"99753","county":"Koyuk"},{"zip":"99754","county":"Koyukuk"},{"zip":"99755","county":"Denali National Park"},{"zip":"99756","county":"Manley Hot Springs"},{"zip":"99757","county":"Lake Minchumina"},{"zip":"99758","county":"Minto"},{"zip":"99759","county":"Point Lay"},{"zip":"99760","county":"Nenana"},{"zip":"99761","county":"Noatak"},{"zip":"99762","county":"Nome"},{"zip":"99763","county":"Noorvik"},{"zip":"99764","county":"Northway"},{"zip":"99765","county":"Nulato"},{"zip":"99766","county":"Point Hope"},{"zip":"99767","county":"Rampart"},{"zip":"99768","county":"Ruby"},{"zip":"99769","county":"Savoonga"},{"zip":"99770","county":"Selawik"},{"zip":"99771","county":"Shaktoolik"},{"zip":"99772","county":"Shishmaref"},{"zip":"99773","county":"Shungnak"},{"zip":"99774","county":"Stevens Village"},{"zip":"99775","county":"Fairbanks"},{"zip":"99776","county":"Tanacross"},{"zip":"99777","county":"Tanana"},{"zip":"99778","county":"Teller"},{"zip":"99779","county":"Tok"},{"zip":"99780","county":"Tok"},{"zip":"99781","county":"Venetie"},{"zip":"99782","county":"Wainwright"},{"zip":"99783","county":"Wales"},{"zip":"99784","county":"White Mountain"},{"zip":"99785","county":"Brevig Mission"},{"zip":"99786","county":"Ambler"},{"zip":"99788","county":"Chalkyitsik"},{"zip":"99789","county":"Nuiqsut"},{"zip":"99790","county":"Fairbanks"},{"zip":"99791","county":"Atqasuk"},{"zip":"99801","county":"Juneau"},{"zip":"99802","county":"Juneau"},{"zip":"99803","county":"Juneau"},{"zip":"99811","county":"Juneau"},{"zip":"99812","county":"Juneau"},{"zip":"99820","county":"Angoon"},{"zip":"99821","county":"Auke Bay"},{"zip":"99824","county":"Douglas"},{"zip":"99825","county":"Elfin Cove"},{"zip":"99826","county":"Gustavus"},{"zip":"99827","county":"Haines"},{"zip":"99829","county":"Hoonah"},{"zip":"99830","county":"Kake"},{"zip":"99832","county":"Pelican"},{"zip":"99833","county":"Petersburg"},{"zip":"99835","county":"Sitka"},{"zip":"99836","county":"Port Alexander"},{"zip":"99840","county":"Skagway"},{"zip":"99841","county":"Tenakee Springs"},{"zip":"99850","county":"Juneau"},{"zip":"99901","county":"Ketchikan"},{"zip":"99903","county":"Meyers Chuck"},{"zip":"99918","county":"Coffman Cove"},{"zip":"99919","county":"Thorne Bay"},{"zip":"99921","county":"Craig"},{"zip":"99922","county":"Hydaburg"},{"zip":"99923","county":"Hyder"},{"zip":"99925","county":"Klawock"},{"zip":"99926","county":"Metlakatla"},{"zip":"99927","county":"Point Baker"},{"zip":"99928","county":"Ward Cove"},{"zip":"99929","county":"Wrangell"},{"zip":"99950","county":"Ketchikan"},{"zip":"85001","county":"Phoenix"},{"zip":"85002","county":"Phoenix"},{"zip":"85003","county":"Phoenix"},{"zip":"85004","county":"Phoenix"},{"zip":"85005","county":"Phoenix"},{"zip":"85006","county":"Phoenix"},{"zip":"85007","county":"Phoenix"},{"zip":"85008","county":"Phoenix"},{"zip":"85009","county":"Phoenix"},{"zip":"85010","county":"Phoenix"},{"zip":"85011","county":"Phoenix"},{"zip":"85012","county":"Phoenix"},{"zip":"85013","county":"Phoenix"},{"zip":"85014","county":"Phoenix"},{"zip":"85015","county":"Phoenix"},{"zip":"85016","county":"Phoenix"},{"zip":"85017","county":"Phoenix"},{"zip":"85018","county":"Phoenix"},{"zip":"85019","county":"Phoenix"},{"zip":"85020","county":"Phoenix"},{"zip":"85021","county":"Phoenix"},{"zip":"85022","county":"Phoenix"},{"zip":"85023","county":"Phoenix"},{"zip":"85024","county":"Phoenix"},{"zip":"85025","county":"Phoenix"},{"zip":"85026","county":"Phoenix"},{"zip":"85027","county":"Phoenix"},{"zip":"85028","county":"Phoenix"},{"zip":"85029","county":"Phoenix"},{"zip":"85030","county":"Phoenix"},{"zip":"85031","county":"Phoenix"},{"zip":"85032","county":"Phoenix"},{"zip":"85033","county":"Phoenix"},{"zip":"85034","county":"Phoenix"},{"zip":"85035","county":"Phoenix"},{"zip":"85036","county":"Phoenix"},{"zip":"85037","county":"Phoenix"},{"zip":"85038","county":"Phoenix"},{"zip":"85039","county":"Phoenix"},{"zip":"85040","county":"Phoenix"},{"zip":"85041","county":"Phoenix"},{"zip":"85042","county":"Phoenix"},{"zip":"85043","county":"Phoenix"},{"zip":"85044","county":"Phoenix"},{"zip":"85045","county":"Phoenix"},{"zip":"85046","county":"Phoenix"},{"zip":"85048","county":"Phoenix"},{"zip":"85050","county":"Phoenix"},{"zip":"85051","county":"Phoenix"},{"zip":"85053","county":"Phoenix"},{"zip":"85054","county":"Phoenix"},{"zip":"85055","county":"Phoenix"},{"zip":"85060","county":"Phoenix"},{"zip":"85061","county":"Phoenix"},{"zip":"85062","county":"Phoenix"},{"zip":"85063","county":"Phoenix"},{"zip":"85064","county":"Phoenix"},{"zip":"85065","county":"Phoenix"},{"zip":"85066","county":"Phoenix"},{"zip":"85067","county":"Phoenix"},{"zip":"85068","county":"Phoenix"},{"zip":"85069","county":"Phoenix"},{"zip":"85070","county":"Phoenix"},{"zip":"85071","county":"Phoenix"},{"zip":"85072","county":"Phoenix"},{"zip":"85073","county":"Phoenix"},{"zip":"85074","county":"Phoenix"},{"zip":"85075","county":"Phoenix"},{"zip":"85076","county":"Phoenix"},{"zip":"85077","county":"Phoenix"},{"zip":"85078","county":"Phoenix"},{"zip":"85079","county":"Phoenix"},{"zip":"85080","county":"Phoenix"},{"zip":"85082","county":"Phoenix"},{"zip":"85085","county":"Phoenix"},{"zip":"85086","county":"Phoenix"},{"zip":"85087","county":"New River"},{"zip":"85098","county":"Phoenix"},{"zip":"85099","county":"Phoenix"},{"zip":"85201","county":"Mesa"},{"zip":"85202","county":"Mesa"},{"zip":"85203","county":"Mesa"},{"zip":"85204","county":"Mesa"},{"zip":"85205","county":"Mesa"},{"zip":"85206","county":"Mesa"},{"zip":"85207","county":"Mesa"},{"zip":"85208","county":"Mesa"},{"zip":"85209","county":"Mesa"},{"zip":"85210","county":"Mesa"},{"zip":"85211","county":"Mesa"},{"zip":"85212","county":"Mesa"},{"zip":"85213","county":"Mesa"},{"zip":"85214","county":"Mesa"},{"zip":"85215","county":"Mesa"},{"zip":"85216","county":"Mesa"},{"zip":"85217","county":"Apache Junction"},{"zip":"85218","county":"Apache Junction"},{"zip":"85219","county":"Apache Junction"},{"zip":"85220","county":"Apache Junction"},{"zip":"85221","county":"Bapchule"},{"zip":"85222","county":"Casa Grande"},{"zip":"85223","county":"Arizona City"},{"zip":"85224","county":"Chandler"},{"zip":"85225","county":"Chandler"},{"zip":"85226","county":"Chandler"},{"zip":"85227","county":"Chandler Heights"},{"zip":"85228","county":"Coolidge"},{"zip":"85230","county":"Casa Grande"},{"zip":"85231","county":"Eloy"},{"zip":"85232","county":"Florence"},{"zip":"85233","county":"Gilbert"},{"zip":"85234","county":"Gilbert"},{"zip":"85235","county":"Hayden"},{"zip":"85236","county":"Higley"},{"zip":"85237","county":"Kearny"},{"zip":"85239","county":"Maricopa"},{"zip":"85241","county":"Picacho"},{"zip":"85242","county":"Queen Creek"},{"zip":"85243","county":"Queen Creek"},{"zip":"85244","county":"Chandler"},{"zip":"85245","county":"Red Rock"},{"zip":"85246","county":"Chandler"},{"zip":"85247","county":"Sacaton"},{"zip":"85248","county":"Chandler"},{"zip":"85249","county":"Chandler"},{"zip":"85250","county":"Scottsdale"},{"zip":"85251","county":"Scottsdale"},{"zip":"85252","county":"Scottsdale"},{"zip":"85253","county":"Paradise Valley"},{"zip":"85254","county":"Scottsdale"},{"zip":"85255","county":"Scottsdale"},{"zip":"85256","county":"Scottsdale"},{"zip":"85257","county":"Scottsdale"},{"zip":"85258","county":"Scottsdale"},{"zip":"85259","county":"Scottsdale"},{"zip":"85260","county":"Scottsdale"},{"zip":"85261","county":"Scottsdale"},{"zip":"85262","county":"Scottsdale"},{"zip":"85263","county":"Rio Verde"},{"zip":"85264","county":"Fort Mcdowell"},{"zip":"85266","county":"Scottsdale"},{"zip":"85267","county":"Scottsdale"},{"zip":"85268","county":"Fountain Hills"},{"zip":"85269","county":"Fountain Hills"},{"zip":"85271","county":"Scottsdale"},{"zip":"85272","county":"Stanfield"},{"zip":"85273","county":"Superior"},{"zip":"85274","county":"Mesa"},{"zip":"85275","county":"Mesa"},{"zip":"85277","county":"Mesa"},{"zip":"85278","county":"Apache Junction"},{"zip":"85279","county":"Florence"},{"zip":"85280","county":"Tempe"},{"zip":"85281","county":"Tempe"},{"zip":"85282","county":"Tempe"},{"zip":"85283","county":"Tempe"},{"zip":"85284","county":"Tempe"},{"zip":"85285","county":"Tempe"},{"zip":"85287","county":"Tempe"},{"zip":"85289","county":"Tempe"},{"zip":"85290","county":"Tortilla Flat"},{"zip":"85291","county":"Valley Farms"},{"zip":"85292","county":"Winkelman"},{"zip":"85296","county":"Gilbert"},{"zip":"85297","county":"Gilbert"},{"zip":"85299","county":"Gilbert"},{"zip":"85301","county":"Glendale"},{"zip":"85302","county":"Glendale"},{"zip":"85303","county":"Glendale"},{"zip":"85304","county":"Glendale"},{"zip":"85305","county":"Glendale"},{"zip":"85306","county":"Glendale"},{"zip":"85307","county":"Glendale"},{"zip":"85308","county":"Glendale"},{"zip":"85309","county":"Glendale Luke Afb"},{"zip":"85310","county":"Glendale"},{"zip":"85311","county":"Glendale"},{"zip":"85312","county":"Glendale"},{"zip":"85313","county":"Glendale"},{"zip":"85318","county":"Glendale"},{"zip":"85320","county":"Aguila"},{"zip":"85321","county":"Ajo"},{"zip":"85322","county":"Arlington"},{"zip":"85323","county":"Avondale"},{"zip":"85324","county":"Black Canyon City"},{"zip":"85325","county":"Bouse"},{"zip":"85326","county":"Buckeye"},{"zip":"85327","county":"Cave Creek"},{"zip":"85328","county":"Cibola"},{"zip":"85329","county":"Cashion"},{"zip":"85331","county":"Cave Creek"},{"zip":"85332","county":"Congress"},{"zip":"85333","county":"Dateland"},{"zip":"85334","county":"Ehrenberg"},{"zip":"85335","county":"El Mirage"},{"zip":"85336","county":"Gadsden"},{"zip":"85337","county":"Gila Bend"},{"zip":"85338","county":"Goodyear"},{"zip":"85339","county":"Laveen"},{"zip":"85340","county":"Litchfield Park"},{"zip":"85341","county":"Lukeville"},{"zip":"85342","county":"Morristown"},{"zip":"85343","county":"Palo Verde"},{"zip":"85344","county":"Parker"},{"zip":"85345","county":"Peoria"},{"zip":"85346","county":"Quartzsite"},{"zip":"85347","county":"Roll"},{"zip":"85348","county":"Salome"},{"zip":"85349","county":"San Luis"},{"zip":"85350","county":"Somerton"},{"zip":"85351","county":"Sun City"},{"zip":"85352","county":"Tacna"},{"zip":"85353","county":"Tolleson"},{"zip":"85354","county":"Tonopah"},{"zip":"85355","county":"Waddell"},{"zip":"85356","county":"Wellton"},{"zip":"85357","county":"Wenden"},{"zip":"85358","county":"Wickenburg"},{"zip":"85359","county":"Quartzsite"},{"zip":"85360","county":"Wikieup"},{"zip":"85361","county":"Wittmann"},{"zip":"85362","county":"Yarnell"},{"zip":"85363","county":"Youngtown"},{"zip":"85364","county":"Yuma"},{"zip":"85365","county":"Yuma"},{"zip":"85366","county":"Yuma"},{"zip":"85367","county":"Yuma"},{"zip":"85369","county":"Yuma"},{"zip":"85371","county":"Poston"},{"zip":"85372","county":"Sun City"},{"zip":"85373","county":"Sun City"},{"zip":"85374","county":"Surprise"},{"zip":"85375","county":"Sun City West"},{"zip":"85376","county":"Sun City West"},{"zip":"85377","county":"Carefree"},{"zip":"85378","county":"Surprise"},{"zip":"85379","county":"Surprise"},{"zip":"85380","county":"Peoria"},{"zip":"85381","county":"Peoria"},{"zip":"85382","county":"Peoria"},{"zip":"85383","county":"Peoria"},{"zip":"85385","county":"Peoria"},{"zip":"85387","county":"Surprise"},{"zip":"85388","county":"Surprise"},{"zip":"85390","county":"Wickenburg"},{"zip":"85396","county":"Buckeye"},{"zip":"85501","county":"Globe"},{"zip":"85502","county":"Globe"},{"zip":"85530","county":"Bylas"},{"zip":"85531","county":"Central"},{"zip":"85532","county":"Claypool"},{"zip":"85533","county":"Clifton"},{"zip":"85534","county":"Duncan"},{"zip":"85535","county":"Eden"},{"zip":"85536","county":"Fort Thomas"},{"zip":"85539","county":"Miami"},{"zip":"85540","county":"Morenci"},{"zip":"85541","county":"Payson"},{"zip":"85542","county":"Peridot"},{"zip":"85543","county":"Pima"},{"zip":"85544","county":"Pine"},{"zip":"85545","county":"Roosevelt"},{"zip":"85546","county":"Safford"},{"zip":"85547","county":"Payson"},{"zip":"85548","county":"Safford"},{"zip":"85550","county":"San Carlos"},{"zip":"85551","county":"Solomon"},{"zip":"85552","county":"Thatcher"},{"zip":"85553","county":"Tonto Basin"},{"zip":"85554","county":"Young"},{"zip":"85601","county":"Arivaca"},{"zip":"85602","county":"Benson"},{"zip":"85603","county":"Bisbee"},{"zip":"85605","county":"Bowie"},{"zip":"85606","county":"Cochise"},{"zip":"85607","county":"Douglas"},{"zip":"85608","county":"Douglas"},{"zip":"85609","county":"Dragoon"},{"zip":"85610","county":"Elfrida"},{"zip":"85611","county":"Elgin"},{"zip":"85613","county":"Fort Huachuca"},{"zip":"85614","county":"Green Valley"},{"zip":"85615","county":"Hereford"},{"zip":"85616","county":"Huachuca City"},{"zip":"85617","county":"Mc Neal"},{"zip":"85618","county":"Mammoth"},{"zip":"85619","county":"Mount Lemmon"},{"zip":"85620","county":"Naco"},{"zip":"85621","county":"Nogales"},{"zip":"85622","county":"Green Valley"},{"zip":"85623","county":"Oracle"},{"zip":"85624","county":"Patagonia"},{"zip":"85625","county":"Pearce"},{"zip":"85626","county":"Pirtleville"},{"zip":"85627","county":"Pomerene"},{"zip":"85628","county":"Nogales"},{"zip":"85629","county":"Sahuarita"},{"zip":"85630","county":"Saint David"},{"zip":"85631","county":"San Manuel"},{"zip":"85632","county":"San Simon"},{"zip":"85633","county":"Sasabe"},{"zip":"85634","county":"Sells"},{"zip":"85635","county":"Sierra Vista"},{"zip":"85636","county":"Sierra Vista"},{"zip":"85637","county":"Sonoita"},{"zip":"85638","county":"Tombstone"},{"zip":"85639","county":"Topawa"},{"zip":"85640","county":"Tumacacori"},{"zip":"85641","county":"Vail"},{"zip":"85643","county":"Willcox"},{"zip":"85644","county":"Willcox"},{"zip":"85645","county":"Amado"},{"zip":"85646","county":"Tubac"},{"zip":"85648","county":"Rio Rico"},{"zip":"85650","county":"Sierra Vista"},{"zip":"85652","county":"Cortaro"},{"zip":"85653","county":"Marana"},{"zip":"85654","county":"Rillito"},{"zip":"85655","county":"Douglas"},{"zip":"85662","county":"Nogales"},{"zip":"85670","county":"Fort Huachuca"},{"zip":"85671","county":"Sierra Vista"},{"zip":"85701","county":"Tucson"},{"zip":"85702","county":"Tucson"},{"zip":"85703","county":"Tucson"},{"zip":"85704","county":"Tucson"},{"zip":"85705","county":"Tucson"},{"zip":"85706","county":"Tucson"},{"zip":"85707","county":"Tucson"},{"zip":"85708","county":"Tucson"},{"zip":"85709","county":"Tucson"},{"zip":"85710","county":"Tucson"},{"zip":"85711","county":"Tucson"},{"zip":"85712","county":"Tucson"},{"zip":"85713","county":"Tucson"},{"zip":"85714","county":"Tucson"},{"zip":"85715","county":"Tucson"},{"zip":"85716","county":"Tucson"},{"zip":"85717","county":"Tucson"},{"zip":"85718","county":"Tucson"},{"zip":"85719","county":"Tucson"},{"zip":"85720","county":"Tucson"},{"zip":"85721","county":"Tucson"},{"zip":"85722","county":"Tucson"},{"zip":"85723","county":"Tucson"},{"zip":"85724","county":"Tucson"},{"zip":"85725","county":"Tucson"},{"zip":"85726","county":"Tucson"},{"zip":"85728","county":"Tucson"},{"zip":"85730","county":"Tucson"},{"zip":"85731","county":"Tucson"},{"zip":"85732","county":"Tucson"},{"zip":"85733","county":"Tucson"},{"zip":"85734","county":"Tucson"},{"zip":"85735","county":"Tucson"},{"zip":"85736","county":"Tucson"},{"zip":"85737","county":"Tucson"},{"zip":"85738","county":"Catalina"},{"zip":"85739","county":"Tucson"},{"zip":"85740","county":"Tucson"},{"zip":"85741","county":"Tucson"},{"zip":"85742","county":"Tucson"},{"zip":"85743","county":"Tucson"},{"zip":"85744","county":"Tucson"},{"zip":"85745","county":"Tucson"},{"zip":"85746","county":"Tucson"},{"zip":"85747","county":"Tucson"},{"zip":"85748","county":"Tucson"},{"zip":"85749","county":"Tucson"},{"zip":"85750","county":"Tucson"},{"zip":"85751","county":"Tucson"},{"zip":"85752","county":"Tucson"},{"zip":"85754","county":"Tucson"},{"zip":"85755","county":"Tucson"},{"zip":"85757","county":"Tucson"},{"zip":"85775","county":"Tucson"},{"zip":"85777","county":"Tucson"},{"zip":"85901","county":"Show Low"},{"zip":"85902","county":"Show Low"},{"zip":"85911","county":"Cibecue"},{"zip":"85912","county":"White Mountain Lake"},{"zip":"85920","county":"Alpine"},{"zip":"85922","county":"Blue"},{"zip":"85923","county":"Clay Springs"},{"zip":"85924","county":"Concho"},{"zip":"85925","county":"Eagar"},{"zip":"85926","county":"Fort Apache"},{"zip":"85927","county":"Greer"},{"zip":"85928","county":"Heber"},{"zip":"85929","county":"Lakeside"},{"zip":"85930","county":"Mcnary"},{"zip":"85931","county":"Forest Lakes"},{"zip":"85932","county":"Nutrioso"},{"zip":"85933","county":"Overgaard"},{"zip":"85934","county":"Pinedale"},{"zip":"85935","county":"Pinetop"},{"zip":"85936","county":"Saint Johns"},{"zip":"85937","county":"Snowflake"},{"zip":"85938","county":"Springerville"},{"zip":"85939","county":"Taylor"},{"zip":"85940","county":"Vernon"},{"zip":"85941","county":"Whiteriver"},{"zip":"85942","county":"Woodruff"},{"zip":"86001","county":"Flagstaff"},{"zip":"86002","county":"Flagstaff"},{"zip":"86003","county":"Flagstaff"},{"zip":"86004","county":"Flagstaff"},{"zip":"86011","county":"Flagstaff"},{"zip":"86015","county":"Bellemont"},{"zip":"86016","county":"Gray Mountain"},{"zip":"86017","county":"Munds Park"},{"zip":"86018","county":"Parks"},{"zip":"86020","county":"Cameron"},{"zip":"86021","county":"Colorado City"},{"zip":"86022","county":"Fredonia"},{"zip":"86023","county":"Grand Canyon"},{"zip":"86024","county":"Happy Jack"},{"zip":"86025","county":"Holbrook"},{"zip":"86028","county":"Petrified Forest Natl Pk"},{"zip":"86029","county":"Sun Valley"},{"zip":"86030","county":"Hotevilla"},{"zip":"86031","county":"Indian Wells"},{"zip":"86032","county":"Joseph City"},{"zip":"86033","county":"Kayenta"},{"zip":"86034","county":"Keams Canyon"},{"zip":"86035","county":"Leupp"},{"zip":"86036","county":"Marble Canyon"},{"zip":"86038","county":"Mormon Lake"},{"zip":"86039","county":"Kykotsmovi Village"},{"zip":"86040","county":"Page"},{"zip":"86042","county":"Polacca"},{"zip":"86043","county":"Second Mesa"},{"zip":"86044","county":"Tonalea"},{"zip":"86045","county":"Tuba City"},{"zip":"86046","county":"Williams"},{"zip":"86047","county":"Winslow"},{"zip":"86052","county":"North Rim"},{"zip":"86053","county":"Kaibeto"},{"zip":"86054","county":"Shonto"},{"zip":"86301","county":"Prescott"},{"zip":"86302","county":"Prescott"},{"zip":"86303","county":"Prescott"},{"zip":"86304","county":"Prescott"},{"zip":"86305","county":"Prescott"},{"zip":"86312","county":"Prescott Valley"},{"zip":"86313","county":"Prescott"},{"zip":"86314","county":"Prescott Valley"},{"zip":"86320","county":"Ash Fork"},{"zip":"86321","county":"Bagdad"},{"zip":"86322","county":"Camp Verde"},{"zip":"86323","county":"Chino Valley"},{"zip":"86324","county":"Clarkdale"},{"zip":"86325","county":"Cornville"},{"zip":"86326","county":"Cottonwood"},{"zip":"86327","county":"Dewey"},{"zip":"86329","county":"Humboldt"},{"zip":"86330","county":"Iron Springs"},{"zip":"86331","county":"Jerome"},{"zip":"86332","county":"Kirkland"},{"zip":"86333","county":"Mayer"},{"zip":"86334","county":"Paulden"},{"zip":"86335","county":"Rimrock"},{"zip":"86336","county":"Sedona"},{"zip":"86337","county":"Seligman"},{"zip":"86338","county":"Skull Valley"},{"zip":"86339","county":"Sedona"},{"zip":"86340","county":"Sedona"},{"zip":"86341","county":"Sedona"},{"zip":"86342","county":"Lake Montezuma"},{"zip":"86343","county":"Crown King"},{"zip":"86351","county":"Sedona"},{"zip":"86401","county":"Kingman"},{"zip":"86402","county":"Kingman"},{"zip":"86403","county":"Lake Havasu City"},{"zip":"86404","county":"Lake Havasu City"},{"zip":"86405","county":"Lake Havasu City"},{"zip":"86406","county":"Lake Havasu City"},{"zip":"86409","county":"Kingman"},{"zip":"86411","county":"Hackberry"},{"zip":"86412","county":"Hualapai"},{"zip":"86413","county":"Golden Valley"},{"zip":"86426","county":"Bullhead City Fort Mohave"},{"zip":"86427","county":"Bullhead City Fort Mohave"},{"zip":"86429","county":"Bullhead City"},{"zip":"86430","county":"Bullhead City"},{"zip":"86431","county":"Chloride"},{"zip":"86432","county":"Littlefield"},{"zip":"86433","county":"Oatman"},{"zip":"86434","county":"Peach Springs"},{"zip":"86435","county":"Supai"},{"zip":"86436","county":"Topock"},{"zip":"86437","county":"Valentine"},{"zip":"86438","county":"Yucca"},{"zip":"86439","county":"Bullhead City"},{"zip":"86440","county":"Bullhead City Mohave Valley"},{"zip":"86441","county":"Dolan Springs"},{"zip":"86442","county":"Bullhead City"},{"zip":"86443","county":"Temple Bar Marina"},{"zip":"86444","county":"Meadview"},{"zip":"86445","county":"Willow Beach"},{"zip":"86446","county":"Bullhead City Mohave Valley"},{"zip":"86502","county":"Chambers"},{"zip":"86503","county":"Chinle"},{"zip":"86504","county":"Fort Defiance"},{"zip":"86505","county":"Ganado"},{"zip":"86506","county":"Houck"},{"zip":"86507","county":"Lukachukai"},{"zip":"86508","county":"Lupton"},{"zip":"86510","county":"Pinon"},{"zip":"86511","county":"Saint Michaels"},{"zip":"86512","county":"Sanders"},{"zip":"86514","county":"Teec Nos Pos"},{"zip":"86515","county":"Window Rock"},{"zip":"86520","county":"Blue Gap"},{"zip":"86535","county":"Dennehotso"},{"zip":"86538","county":"Many Farms"},{"zip":"86540","county":"Nazlini"},{"zip":"86544","county":"Red Valley"},{"zip":"86545","county":"Rock Point"},{"zip":"86547","county":"Round Rock"},{"zip":"86556","county":"Tsaile"}]